{"type": "Feature", "geometry": {"type": "Polygon", "coordinates": [[[18.559999999999945, 42.64999999999998], [18.706480000000056, 43.200109999999995], [19.03165000000007, 43.432529999999986], [19.218519999999955, 43.52384000000001], [19.454000000000065, 43.56810000000013], [19.59976000000006, 44.03846999999996], [19.11761000000007, 44.42307000000011], [19.36802999999992, 44.863000000000056], [19.00548000000009, 44.86023], [19.005484597557594, 44.86023449354299], [18.553214145591653, 45.08158966733146], [17.861783481526402, 45.067740383477144], [17.002146030351014, 45.23377676043094], [16.534939406000206, 45.21160757097772], [16.318156772535872, 45.00412669532591], [15.959367303133376, 45.23377676043094], [15.750026075918981, 44.818711656262565], [16.23966027188453, 44.35114329688571], [16.456442905348865, 44.04123973243128], [16.91615644701733, 43.66772247982567], [17.297373488034452, 43.44634064388737], [17.674921502358984, 43.02856252702361], [18.559999999999945, 42.64999999999998]]]}, "properties": {"featurecla": "Admin-0 country", "scalerank": 1, "LABELRANK": 5, "SOVEREIGNT": "Bosnia and Herzegovina", "SOV_A3": "BIH", "ADM0_DIF": 0, "LEVEL": 2, "TYPE": "Sovereign country", "ADMIN": "Bosnia and Herzegovina", "ADM0_A3": "BIH", "GEOU_DIF": 0, "GEOUNIT": "Bosnia and Herzegovina", "GU_A3": "BIH", "SU_DIF": 0, "SUBUNIT": "Bosnia and Herzegovina", "SU_A3": "BIH", "BRK_DIFF": 0, "NAME": "Bosnia and Herz.", "NAME_LONG": "Bosnia and Herzegovina", "BRK_A3": "BIH", "BRK_NAME": "Bosnia and Herz.", "BRK_GROUP": "", "ABBREV": "B.H.", "POSTAL": "BiH", "FORMAL_EN": "Bosnia and Herzegovina", "FORMAL_FR": "", "NAME_CIAWF": "Bosnia and Herzegovina", "NOTE_ADM0": "", "NOTE_BRK": "", "NAME_SORT": "Bosnia and Herzegovina", "NAME_ALT": "", "MAPCOLOR7": 1, "MAPCOLOR8": 1, "MAPCOLOR9": 1, "MAPCOLOR13": 2, "POP_EST": 3856181, "POP_RANK": 12, "GDP_MD_EST": 42530, "POP_YEAR": 2017, "LASTCENSUS": 1991, "GDP_YEAR": 2016, "ECONOMY": "6. Developing region", "INCOME_GRP": "3. Upper middle income", "WIKIPEDIA": -99, "FIPS_10_": "BK", "ISO_A2": "BA", "ISO_A3": "BIH", "ISO_A3_EH": "BIH", "ISO_N3": "070", "UN_A3": "070", "WB_A2": "BA", "WB_A3": "BIH", "WOE_ID": 23424761, "WOE_ID_EH": 23424761, "WOE_NOTE": "Exact WOE match as country", "ADM0_A3_IS": "BIH", "ADM0_A3_US": "BIH", "ADM0_A3_UN": -99, "ADM0_A3_WB": -99, "CONTINENT": "Europe", "REGION_UN": "Europe", "SUBREGION": "Southern Europe", "REGION_WB": "Europe & Central Asia", "NAME_LEN": 16, "LONG_LEN": 22, "ABBREV_LEN": 4, "TINY": -99, "HOMEPART": 1, "MIN_ZOOM": 0, "MIN_LABEL": 4.5, "MAX_LABEL": 9.5, "NE_ID": 1159320417, "WIKIDATAID": "Q225", "NAME_AR": "\u0627\u0644\u0628\u0648\u0633\u0646\u0629 \u0648\u0627\u0644\u0647\u0631\u0633\u0643", "NAME_BN": "\u09ac\u09b8\u09a8\u09bf\u09af\u09bc\u09be \u0993 \u09b9\u09be\u09b0\u09cd\u099c\u09c7\u0997\u09cb\u09ad\u09bf\u09a8\u09be", "NAME_DE": "Bosnien und Herzegowina", "NAME_EN": "Bosnia and Herzegovina", "NAME_ES": "Bosnia y Herzegovina", "NAME_FR": "Bosnie-Herz\u00e9govine", "NAME_EL": "\u0392\u03bf\u03c3\u03bd\u03af\u03b1 \u03ba\u03b1\u03b9 \u0395\u03c1\u03b6\u03b5\u03b3\u03bf\u03b2\u03af\u03bd\u03b7", "NAME_HI": "\u092c\u0949\u0938\u094d\u0928\u093f\u092f\u093e \u0914\u0930 \u0939\u0930\u094d\u091c\u093c\u0947\u0917\u094b\u0935\u093f\u0928\u093e", "NAME_HU": "Bosznia-Hercegovina", "NAME_ID": "Bosnia dan Herzegovina", "NAME_IT": "Bosnia ed Erzegovina", "NAME_JA": "\u30dc\u30b9\u30cb\u30a2\u30fb\u30d8\u30eb\u30c4\u30a7\u30b4\u30d3\u30ca", "NAME_KO": "\ubcf4\uc2a4\ub2c8\uc544 \ud5e4\ub974\uccb4\uace0\ube44\ub098", "NAME_NL": "Bosni\u00eb en Herzegovina", "NAME_PL": "Bo\u015bnia i Hercegowina", "NAME_PT": "B\u00f3snia e Herzegovina", "NAME_RU": "\u0411\u043e\u0441\u043d\u0438\u044f \u0438 \u0413\u0435\u0440\u0446\u0435\u0433\u043e\u0432\u0438\u043d\u0430", "NAME_SV": "Bosnien och Hercegovina", "NAME_TR": "Bosna-Hersek", "NAME_VI": "Bosna v\u00e0 Hercegovina", "NAME_ZH": "\u6ce2\u65af\u5c3c\u4e9a\u548c\u9ed1\u585e\u54e5\u7ef4\u90a3"}}