{"type": "FeatureCollection", "features": [{"type": "Feature", "geometry": {"type": "Polygon", "coordinates": [[[-24.704335089999915, 14.900824286000045], [-24.693104620999918, 14.890692450000074], [-24.686756964999915, 14.876166083000044], [-24.683949347999942, 14.859442450000074], [-24.683257615999935, 14.842474677000041], [-24.686879035999937, 14.826646226000037], [-24.695301886999914, 14.81940338700008], [-24.704416469999956, 14.814032294000071], [-24.710560675999943, 14.803941148000092], [-24.718006964999915, 14.803941148000092], [-24.725453253999945, 14.814113674000055], [-24.744618292999917, 14.826605536000045], [-24.75153561099995, 14.838771877000056], [-24.758941209999932, 14.831854559000078], [-24.754709438999953, 14.84080638200004], [-24.753244594999956, 14.849351304000038], [-24.754709438999953, 14.857855536000045], [-24.758941209999932, 14.86664459800005], [-24.745350714999915, 14.86664459800005], [-24.74941972599993, 14.88548411700009], [-24.737619594999956, 14.89203522300005], [-24.719349738999938, 14.89443594000005], [-24.704335089999915, 14.900824286000045]]]}, "properties": {"featurecla": "Admin-1 scale rank", "scalerank": 5, "adm1_code": "CPV-5041", "diss_me": 5041, "iso_3166_2": "CV-BR", "wikipedia": "http://en.wikipedia.org/wiki/Brava_(Cape_Verde)", "iso_a2": "CV", "adm0_sr": 3, "name": "Brava", "name_alt": "", "name_local": "", "type": "", "type_en": "", "code_local": "91", "code_hasc": "CV.BR", "note": "", "hasc_maybe": "", "region": "Ilhas de Sotavento", "region_cod": "CV-S", "provnum_ne": 0, "gadm_level": 0, "check_me": 0, "datarank": 10, "abbrev": "", "postal": "BR", "area_sqkm": 0, "sameascity": -99, "labelrank": 20, "name_len": 5, "mapcolor9": 4, "mapcolor13": 11, "fips": "CV02", "fips_alt": "", "woe_id": 2345122, "woe_label": "Brava, CV, Cape Verde", "woe_name": "Brava", "latitude": 14.851, "longitude": -24.7204, "sov_a3": "CPV", "adm0_a3": "CPV", "adm0_label": 2, "admin": "Cape Verde", "geonunit": "Cape Verde", "gu_a3": "CPV", "gn_id": 3374832, "gn_name": "Concelho da Brava", "gns_id": -1312969, "gns_name": "Brava", "gn_level": 1, "gn_region": "", "gn_a1_code": "CV.02", "region_sub": "", "sub_code": "", "gns_level": 1, "gns_lang": "por", "gns_adm1": "CV02", "gns_region": "", "min_label": 11, "max_label": 11, "min_zoom": 11, "wikidataid": "Q2571624", "name_ar": "\u0628\u0631\u0627\u0641\u0627", "name_bn": "\u09ac\u09cd\u09b0\u09be\u09ad\u09be", "name_de": "Brava", "name_en": "Brava", "name_es": "Brava", "name_fr": "Brava", "name_el": "\u039c\u03c0\u03c1\u03ac\u03b2\u03b1", "name_hi": "\u092c\u094d\u0930\u093e\u0935\u093e", "name_hu": "", "name_id": "Brava", "name_it": "contea di Brava", "name_ja": "\u30d6\u30e9\u30f4\u30a1", "name_ko": "\ube0c\ub77c\ubc14 \uc2dc", "name_nl": "Brava", "name_pl": "Brava", "name_pt": "Brava", "name_ru": "\u0411\u0440\u0430\u0432\u0430", "name_sv": "Brava", "name_tr": "Brava", "name_vi": "Brava", "name_zh": "\u5e03\u62c9\u74e6\u5cf6\u7e23", "ne_id": 1159315639}}, {"type": "Feature", "geometry": {"type": "Polygon", "coordinates": [[[-24.30147575151886, 14.954845976954875], [-24.295765753999945, 14.930487372000073], [-24.296538865999935, 14.917547919000071], [-24.301503058999913, 14.90648021000004], [-24.298207160999937, 14.895453192000048], [-24.320866638384643, 14.872773915383846], [-24.352951099913355, 14.869565469770578], [-24.373805999547244, 14.885607700534933], [-24.383431338185687, 14.908066823425145], [-24.378618668416834, 14.927317499802768], [-24.374044233554514, 14.944917754750577], [-24.337925827015283, 14.953126483100675], [-24.30147575151886, 14.954845976954875]]]}, "properties": {"featurecla": "Admin-1 scale rank", "scalerank": 5, "adm1_code": "CPV-5044", "diss_me": 5044, "iso_3166_2": "CV-CF", "wikipedia": "http://en.wikipedia.org/wiki/Santa_Catarina_do_Fogo", "iso_a2": "CV", "adm0_sr": 3, "name": "Santa Catarina do Fogo", "name_alt": "", "name_local": "", "type": "", "type_en": "", "code_local": "82", "code_hasc": "CV.CF", "note": "", "hasc_maybe": "", "region": "Ilhas de Sotavento", "region_cod": "CV-S", "provnum_ne": 0, "gadm_level": 0, "check_me": 0, "datarank": 10, "abbrev": "", "postal": "CF", "area_sqkm": 0, "sameascity": -99, "labelrank": 20, "name_len": 22, "mapcolor9": 4, "mapcolor13": 11, "fips": "CV24", "fips_alt": "", "woe_id": 56051565, "woe_label": "", "woe_name": "Santa Catarina do Fogo", "latitude": 14.9241, "longitude": -24.3301, "sov_a3": "CPV", "adm0_a3": "CPV", "adm0_label": 2, "admin": "Cape Verde", "geonunit": "Cape Verde", "gu_a3": "CPV", "gn_id": 7602870, "gn_name": "Concelho de Santa Catarina do Fogo", "gns_id": 10874226, "gns_name": "Santa Catarina do Fogo, Concelho de", "gn_level": 1, "gn_region": "", "gn_a1_code": "CV.24", "region_sub": "", "sub_code": "", "gns_level": 1, "gns_lang": "por", "gns_adm1": "CV24", "gns_region": "", "min_label": 11, "max_label": 11, "min_zoom": 11, "wikidataid": "Q2608046", "name_ar": "\u0633\u0627\u0646\u062a\u0627 \u0643\u0627\u062a\u0627\u0631\u064a\u0646\u0627 \u062f\u0648 \u0641\u0648\u062c\u0648", "name_bn": "\u09b8\u09cd\u09af\u09be\u09a8\u09cd\u099f\u09be \u0995\u09cd\u09af\u09be\u099f\u09be\u09b0\u09bf\u09a8\u09be \u09a6\u09cb \u09ab\u09cb\u0997\u09cb", "name_de": "Santa Catarina do Fogo", "name_en": "Santa Catarina do Fogo", "name_es": "Santa Catarina do Fogo", "name_fr": "Santa Catarina do Fogo", "name_el": "\u03a3\u03ac\u03bd\u03c4\u03b1 \u039a\u03b1\u03c4\u03b1\u03c1\u03af\u03bd\u03b1 \u03bd\u03c4\u03bf \u03a6\u03cc\u03c1\u03b3\u03ba\u03bf", "name_hi": "\u0938\u0948\u0902\u091f\u093e \u0915\u0948\u091f\u0930\u0940\u0928\u093e \u0921\u094b \u092b\u094b\u0917\u094b", "name_hu": "", "name_id": "Santa Catarina do Fogo", "name_it": "contea di Santa Catarina do Fogo", "name_ja": "\u30b5\u30f3\u30bf\u30fb\u30ab\u30bf\u30ea\u30ca\u30fb\u30c9\u30fb\u30d5\u30a9\u30b4", "name_ko": "\uc0b0\ud0c0\uce74\ud0c0\ub9ac\ub098\ub450\ud3ec\uad6c \uc2dc", "name_nl": "Santa Catarina do Fogo", "name_pl": "Santa Catarina do Fogo", "name_pt": "Santa Catarina do Fogo", "name_ru": "\u0421\u0430\u043d\u0442\u0430-\u041a\u0430\u0442\u0430\u0440\u0438\u043d\u0430-\u0434\u043e-\u0424\u043e\u0433\u043e", "name_sv": "Concelho de Santa Catarina do Fogo", "name_tr": "Santa Catarina do Fogo", "name_vi": "Santa Catarina do Fogo", "name_zh": "\u798f\u6208\u8056\u5361\u5854\u7433\u5a1c\u7e23", "ne_id": 1159316309}}, {"type": "Feature", "geometry": {"type": "Polygon", "coordinates": [[[-24.42969106395393, 15.025015233310253], [-24.40343176999994, 15.038031317000048], [-24.385568813999953, 15.043524481000077], [-24.364857550999943, 15.045396226000037], [-24.34325110599991, 15.040716864000046], [-24.32921301999994, 15.028713283000059], [-24.320139126999948, 15.013006903000075], [-24.307240363999938, 14.979437567000048], [-24.30147575151886, 14.954845976954875], [-24.337925827015283, 14.953126483100675], [-24.374044233554514, 14.944917754750577], [-24.406879149653037, 14.990886636209268], [-24.42969106395393, 15.025015233310253]]]}, "properties": {"featurecla": "Admin-1 scale rank", "scalerank": 5, "adm1_code": "CPV-5043", "diss_me": 5043, "iso_3166_2": "CV-MO", "wikipedia": "http://en.wikipedia.org/wiki/Mosteiros_(municipality)", "iso_a2": "CV", "adm0_sr": 3, "name": "Mosteiros", "name_alt": "", "name_local": "", "type": "", "type_en": "", "code_local": "81", "code_hasc": "CV.MO", "note": "", "hasc_maybe": "", "region": "Ilhas de Sotavento", "region_cod": "CV-S", "provnum_ne": 0, "gadm_level": 0, "check_me": 0, "datarank": 10, "abbrev": "", "postal": "MO", "area_sqkm": 0, "sameascity": -99, "labelrank": 20, "name_len": 9, "mapcolor9": 4, "mapcolor13": 11, "fips": "CV13", "fips_alt": "", "woe_id": 56051566, "woe_label": "Mosteiros, CV, Cape Verde", "woe_name": "Mosteiros", "latitude": 15.0008, "longitude": -24.3541, "sov_a3": "CPV", "adm0_a3": "CPV", "adm0_label": 2, "admin": "Cape Verde", "geonunit": "Cape Verde", "gu_a3": "CPV", "gn_id": 3411924, "gn_name": "Concelho dos Mosteiros", "gns_id": 9146337, "gns_name": "Mosteiros", "gn_level": 1, "gn_region": "", "gn_a1_code": "CV.13", "region_sub": "", "sub_code": "", "gns_level": 1, "gns_lang": "por", "gns_adm1": "CV13", "gns_region": "", "min_label": 11, "max_label": 11, "min_zoom": 11, "wikidataid": "Q516835", "name_ar": "\u0645\u0648\u0633\u062a\u064a\u0631\u0648\u0633\u060c \u0627\u0644\u0631\u0623\u0633 \u0627\u0644\u0623\u062e\u0636\u0631", "name_bn": "\u09ae\u09b8\u09cd\u099f\u09c7\u0987\u09b0\u09cb\u09b8", "name_de": "Mosteiros", "name_en": "Mosteiros", "name_es": "Mosteiros", "name_fr": "Mosteiros", "name_el": "\u039c\u03bf\u03c3\u03c4\u03ad\u03b9\u03c1\u03bf\u03c2", "name_hi": "\u092e\u094b\u0938\u094d\u091f\u093e\u092f\u0930\u094b\u0938", "name_hu": "", "name_id": "Mosteiros", "name_it": "contea di Mosteiros", "name_ja": "\u30e2\u30b7\u30e5\u30c6\u30a4\u30db\u30b7\u30e5", "name_ko": "\ubaa8\uc2a4\ud14c\uc774\ub8e8\uc2a4 \uc2dc", "name_nl": "Mosteiros", "name_pl": "Mosteiros", "name_pt": "Mosteiros", "name_ru": "\u041c\u043e\u0448\u0442\u0435\u0439\u0440\u0443\u0448", "name_sv": "Concelho dos Mosteiros", "name_tr": "Mosteiros", "name_vi": "Mosteiros", "name_zh": "\u83ab\u4ec0\u6cf0\u9b6f\u4ec0\u7e23", "ne_id": 1159316305}}, {"type": "Feature", "geometry": {"type": "Polygon", "coordinates": [[[-24.298207160999937, 14.895453192000048], [-24.29328365799995, 14.884344794000071], [-24.29283606699994, 14.872870184000078], [-24.299549933999913, 14.863023179000038], [-24.334462042999917, 14.831854559000078], [-24.37653561099995, 14.815985419000071], [-24.41502844999991, 14.820868231000077], [-24.44908606699994, 14.838080145000049], [-24.506581183999913, 14.884955145000049], [-24.520375128999945, 14.903957424000055], [-24.526234503999945, 14.924709377000056], [-24.52061926999994, 14.945257880000042], [-24.506743943999936, 14.969183661000045], [-24.48892167899993, 14.99054596600007], [-24.464588995999918, 15.00771719000005], [-24.42969106395393, 15.025015233310253], [-24.406879149653037, 14.990886636209268], [-24.374044233554514, 14.944917754750577], [-24.378618668416834, 14.927317499802768], [-24.383431338185687, 14.908066823425145], [-24.373805999547244, 14.885607700534933], [-24.352951099913355, 14.869565469770578], [-24.320866638384643, 14.872773915383846], [-24.298207160999937, 14.895453192000048]]]}, "properties": {"featurecla": "Admin-1 scale rank", "scalerank": 5, "adm1_code": "CPV-5042", "diss_me": 5042, "iso_3166_2": "CV-SF", "wikipedia": "http://en.wikipedia.org/wiki/S%C3%A3o_Filipe_(municipality)", "iso_a2": "CV", "adm0_sr": 3, "name": "S\u00e3o Filipe", "name_alt": "", "name_local": "", "type": "", "type_en": "", "code_local": "82", "code_hasc": "CV.FP", "note": "", "hasc_maybe": "", "region": "Ilhas de Sotavento", "region_cod": "CV-S", "provnum_ne": 0, "gadm_level": 0, "check_me": 0, "datarank": 10, "abbrev": "", "postal": "SF", "area_sqkm": 0, "sameascity": -99, "labelrank": 20, "name_len": 10, "mapcolor9": 4, "mapcolor13": 11, "fips": "CV18", "fips_alt": "", "woe_id": 56051564, "woe_label": "S\u00c3\u00a3o Filipe, CV, Cape Verde", "woe_name": "S\u00c3\u00a3o Filipe", "latitude": 14.9241, "longitude": -24.4403, "sov_a3": "CPV", "adm0_a3": "CPV", "adm0_label": 2, "admin": "Cape Verde", "geonunit": "Cape Verde", "gu_a3": "CPV", "gn_id": 3411927, "gn_name": "Concelho do Sao Filipe", "gns_id": 9146429, "gns_name": "Sao Filipe, Concelho do", "gn_level": 1, "gn_region": "", "gn_a1_code": "CV.18", "region_sub": "", "sub_code": "", "gns_level": 1, "gns_lang": "por", "gns_adm1": "CV18", "gns_region": "", "min_label": 11, "max_label": 11, "min_zoom": 11, "wikidataid": "Q6430079", "name_ar": "\u0633\u0627\u0648 \u0641\u064a\u0644\u064a\u0628", "name_bn": "\u09b8\u09be\u0981\u0993 \u09ab\u09bf\u09b2\u09bf\u09aa", "name_de": "S\u00e3o Filipe", "name_en": "S\u00e3o Filipe", "name_es": "S\u00e3o Filipe", "name_fr": "S\u00e3o Filipe", "name_el": "\u03a3\u03ac\u03bf \u03a6\u03b9\u03bb\u03af\u03c0\u03b5", "name_hi": "\u0938\u093e\u0913 \u092b\u093f\u0932\u093f\u092a", "name_hu": "", "name_id": "S\u00e3o Filipe", "name_it": "contea di S\u00e3o Filipe", "name_ja": "\u30b5\u30f3\u30fb\u30d5\u30a3\u30ea\u30da", "name_ko": "\uc0c1\ud544\ub9ac\ud504 \uc2dc", "name_nl": "S\u00e3o Filipe", "name_pl": "S\u00e3o Filipe", "name_pt": "S\u00e3o Filipe", "name_ru": "\u0421\u0430\u043d-\u0424\u0435\u043b\u0438\u043f\u0435", "name_sv": "Concelho do S\u00e3o Filipe", "name_tr": "Sao Filipe", "name_vi": "S\u00e3o Filipe", "name_zh": "\u8056\u83f2\u5229\u4f69\u7e23", "ne_id": 1159316303}}, {"type": "Feature", "geometry": {"type": "Polygon", "coordinates": [[[-23.770130988999938, 15.183986721000053], [-23.766753709999932, 15.193752346000053], [-23.76585852799991, 15.205511786000045], [-23.763661261999914, 15.216294664000088], [-23.758697068999936, 15.223089911000045], [-23.75381425699993, 15.228094794000071], [-23.751576300999943, 15.23346588700008], [-23.75495357999995, 15.25031159100007], [-23.763295050999943, 15.26976146000004], [-23.77440344999991, 15.285630601000037], [-23.785755988999938, 15.291815497000073], [-23.779123501999948, 15.294134833000044], [-23.758412238999938, 15.304877020000049], [-23.773060675999943, 15.310614325000074], [-23.77953040299991, 15.311672268000052], [-23.751576300999943, 15.33274974200009], [-23.744130011999914, 15.33274974200009], [-23.74356035099993, 15.325140692000048], [-23.742014126999948, 15.32094961100006], [-23.739898240999935, 15.317328192000048], [-23.737945115999935, 15.311672268000052], [-23.719227667999917, 15.32290273600006], [-23.703236456999946, 15.31346263200004], [-23.697824673999946, 15.29633209800005], [-23.710682745999918, 15.284369208000044], [-23.697336391999954, 15.266017971000053], [-23.681752081999946, 15.254828192000048], [-23.648548956999946, 15.237209377000056], [-23.656076626999948, 15.229722398000092], [-23.670380478776053, 15.206541459320874], [-23.685882574920925, 15.184395608070815], [-23.72463781438364, 15.17996643800069], [-23.75453471370605, 15.183288316002972], [-23.770130988999938, 15.183986721000053]]]}, "properties": {"featurecla": "Admin-1 scale rank", "scalerank": 5, "adm1_code": "CPV-5045", "diss_me": 5045, "iso_3166_2": "CV-TA", "wikipedia": "http://en.wikipedia.org/wiki/Tarrafal_(municipality)", "iso_a2": "CV", "adm0_sr": 3, "name": "Tarrafal", "name_alt": "", "name_local": "", "type": "", "type_en": "", "code_local": "71", "code_hasc": "CV.TF", "note": "", "hasc_maybe": "", "region": "Ilhas de Sotavento", "region_cod": "CV-S", "provnum_ne": 0, "gadm_level": 0, "check_me": 0, "datarank": 10, "abbrev": "", "postal": "TA", "area_sqkm": 0, "sameascity": -99, "labelrank": 20, "name_len": 8, "mapcolor9": 4, "mapcolor13": 11, "fips": "CV20", "fips_alt": "", "woe_id": 2345131, "woe_label": "Tarrafal, CV, Cape Verde", "woe_name": "Tarrafal", "latitude": 15.2355, "longitude": -23.717, "sov_a3": "CPV", "adm0_a3": "CPV", "adm0_label": 2, "admin": "Cape Verde", "geonunit": "Cape Verde", "gu_a3": "CPV", "gn_id": 3374161, "gn_name": "Concelho do Tarrafal", "gns_id": -1313640, "gns_name": "Tarrafal", "gn_level": 1, "gn_region": "", "gn_a1_code": "CV.20", "region_sub": "", "sub_code": "", "gns_level": 1, "gns_lang": "por", "gns_adm1": "CV20", "gns_region": "", "min_label": 11, "max_label": 11, "min_zoom": 11, "wikidataid": "Q499598", "name_ar": "\u062a\u0627\u0631\u0641\u0627\u0644", "name_bn": "\u09a4\u09be\u09b0\u09be\u09ab\u09be\u09b2", "name_de": "Tarrafal", "name_en": "Tarrafal", "name_es": "Tarrafal", "name_fr": "Tarrafal", "name_el": "\u0394\u03ae\u03bc\u03bf\u03c2 \u03a4\u03b1\u03c1\u03c1\u03b1\u03c6\u03ac\u03bb", "name_hi": "\u0924\u093e\u0930\u094d\u0930\u093e\u092b\u0932", "name_hu": "", "name_id": "Tarrafal", "name_it": "contea di Tarrafal", "name_ja": "\u30bf\u30e9\u30d5\u30a1\u30eb", "name_ko": "\ud0c0\ud558\ud314 \uc2dc", "name_nl": "Tarrafal", "name_pl": "Tarrafal", "name_pt": "Tarrafal", "name_ru": "\u0422\u0430\u0440\u0440\u0430\u0444\u0430\u043b", "name_sv": "Concelho do Tarrafal", "name_tr": "Tarrafal", "name_vi": "Tarrafal", "name_zh": "\u5854\u62c9\u6cd5\u723e\u7e23", "ne_id": 1159316311}}, {"type": "Feature", "geometry": {"type": "Polygon", "coordinates": [[[-23.71507727819386, 14.968451239233275], [-23.730539516999954, 14.985825914000088], [-23.73070227799991, 15.018500067000048], [-23.74205481699994, 15.02635325700004], [-23.758290167999917, 15.031317450000074], [-23.772084113999938, 15.037990627000056], [-23.772694464999915, 15.041693427000041], [-23.77953040299991, 15.064642645000049], [-23.78229732999995, 15.068548895000049], [-23.786284959999932, 15.072414455000057], [-23.79010982999995, 15.077704169000071], [-23.792591925999943, 15.085760809000078], [-23.789865688999953, 15.093817450000074], [-23.77562415299991, 15.11823151200008], [-23.772084113999938, 15.127346096000053], [-23.77293860599991, 15.140448309000078], [-23.785755988999938, 15.174505927000041], [-23.776193813999953, 15.177232164000088], [-23.770130988999938, 15.183986721000053], [-23.75453471370605, 15.183288316002972], [-23.72463781438364, 15.17996643800069], [-23.685882574920925, 15.184395608070815], [-23.686989866988768, 15.166678926890938], [-23.66816589374099, 15.148962246610381], [-23.650449212561114, 15.136782027568529], [-23.64823462752605, 15.121279932322977], [-23.640483579453644, 15.119065347287915], [-23.62660042127243, 15.131405931638426], [-23.620552313238647, 15.123494517358097], [-23.618337728203585, 15.105777836178163], [-23.64188652454345, 15.087342240551948], [-23.647959111223997, 15.081876912989117], [-23.64431555921567, 15.063051895628462], [-23.637028455199072, 15.049084947612243], [-23.629410653378955, 15.0393402824281], [-23.639376286486424, 15.02826735635341], [-23.641590872420807, 15.013872553175759], [-23.649341919593894, 15.009443383105634], [-23.670380478776053, 15.007228798070571], [-23.67923881891636, 14.993941286960819], [-23.698062793063457, 14.986190238888412], [-23.71507727819386, 14.968451239233275]]]}, "properties": {"featurecla": "Admin-1 scale rank", "scalerank": 5, "adm1_code": "CPV-5046", "diss_me": 5046, "iso_3166_2": "CV-CA", "wikipedia": "http://en.wikipedia.org/wiki/Santa_Catarina_(Cape_Verde)", "iso_a2": "CV", "adm0_sr": 3, "name": "Santa Catarina", "name_alt": "", "name_local": "", "type": "", "type_en": "", "code_local": "72", "code_hasc": "CV.CT", "note": "", "hasc_maybe": "", "region": "Ilhas de Sotavento", "region_cod": "CV-S", "provnum_ne": 0, "gadm_level": 0, "check_me": 0, "datarank": 10, "abbrev": "", "postal": "CA", "area_sqkm": 0, "sameascity": -99, "labelrank": 20, "name_len": 14, "mapcolor9": 4, "mapcolor13": 11, "fips": "CV15", "fips_alt": "", "woe_id": 2345128, "woe_label": "Santa Catarina, CV, Cape Verde", "woe_name": "Santa Catarina", "latitude": 15.0918, "longitude": -23.7027, "sov_a3": "CPV", "adm0_a3": "CPV", "adm0_label": 2, "admin": "Cape Verde", "geonunit": "Cape Verde", "gu_a3": "CPV", "gn_id": 3374226, "gn_name": "Concelho de Santa Catarina", "gns_id": -1313575, "gns_name": "Santa Catarina", "gn_level": 1, "gn_region": "", "gn_a1_code": "CV.15", "region_sub": "", "sub_code": "", "gns_level": 1, "gns_lang": "por", "gns_adm1": "CV15", "gns_region": "", "min_label": 11, "max_label": 11, "min_zoom": 11, "wikidataid": "Q494882", "name_ar": "\u0633\u0627\u0646\u062a\u0627 \u0643\u0627\u062a\u0627\u0631\u064a\u0646\u0627", "name_bn": "\u09b8\u09cd\u09af\u09be\u09a8\u09cd\u099f\u09be \u0995\u09cd\u09af\u09be\u099f\u09be\u09b0\u09bf\u09a8\u09be", "name_de": "Santa Catarina", "name_en": "Santa Catarina", "name_es": "Santa Catarina", "name_fr": "Santa Catarina", "name_el": "\u0394\u03ae\u03bc\u03bf\u03c2 \u03a3\u03ac\u03bd\u03c4\u03b1 \u039a\u03b1\u03c4\u03b1\u03c1\u03af\u03bd\u03b1", "name_hi": "\u0938\u0948\u0902\u091f\u093e \u0915\u0948\u091f\u0930\u0940\u0928\u093e", "name_hu": "", "name_id": "Santa Catarina", "name_it": "contea di Santa Catarina", "name_ja": "\u30b5\u30f3\u30bf\u30fb\u30ab\u30bf\u30ea\u30ca", "name_ko": "\uc0b0\ud0c0\uce74\ud0c0\ub9ac\ub098 \uc2dc", "name_nl": "Santa Catarina", "name_pl": "Santa Catarina", "name_pt": "Santa Catarina", "name_ru": "\u0421\u0430\u043d\u0442\u0430-\u041a\u0430\u0442\u0430\u0440\u0438\u043d\u0430", "name_sv": "Concelho de Santa Catarina", "name_tr": "Santa Catarina", "name_vi": "Santa Catarina", "name_zh": "\u8056\u5361\u5854\u7433\u5a1c\u7e23", "ne_id": 1159316313}}, {"type": "Feature", "geometry": {"type": "Polygon", "coordinates": [[[-23.53929602799991, 14.907619533000059], [-23.547352667999917, 14.90851471600007], [-23.555816209999932, 14.912787177000041], [-23.563221808999913, 14.913804429000038], [-23.596424933999913, 14.914536851000037], [-23.62413489499994, 14.918117580000057], [-23.649728969999956, 14.92649974200009], [-23.676503058999913, 14.93553294500009], [-23.71507727819386, 14.968451239233275], [-23.698062793063457, 14.986190238888412], [-23.67923881891636, 14.993941286960819], [-23.670380478776053, 15.007228798070571], [-23.649341919593894, 15.009443383105634], [-23.641590872420807, 15.013872553175759], [-23.639376286486424, 15.02826735635341], [-23.629410653378955, 15.0393402824281], [-23.612038867599665, 15.040919536007777], [-23.611693973098397, 15.024945479250448], [-23.596191876953583, 15.011657968140696], [-23.584011658810994, 14.995048579927982], [-23.58068978080877, 14.968473558607855], [-23.564080392596054, 14.96072251053539], [-23.560464903032823, 14.941755507310802], [-23.547631118781112, 14.925713277445766], [-23.53929602799991, 14.907619533000059]]]}, "properties": {"featurecla": "Admin-1 scale rank", "scalerank": 5, "adm1_code": "CPV-5052", "diss_me": 5052, "iso_3166_2": "CV-RS", "wikipedia": "http://en.wikipedia.org/wiki/Ribeira_Grande_de_Santiago", "iso_a2": "CV", "adm0_sr": 3, "name": "Ribeira Grande de Santiago", "name_alt": "", "name_local": "", "type": "", "type_en": "", "code_local": "74", "code_hasc": "CV.RS", "note": "", "hasc_maybe": "", "region": "Ilhas de Sotavento", "region_cod": "CV-S", "provnum_ne": 0, "gadm_level": 0, "check_me": 0, "datarank": 10, "abbrev": "", "postal": "RS", "area_sqkm": 0, "sameascity": -99, "labelrank": 20, "name_len": 26, "mapcolor9": 4, "mapcolor13": 11, "fips": "CV23", "fips_alt": "", "woe_id": 56051563, "woe_label": "Ribeira Grande, CV, Cape Verde", "woe_name": "Ribeira Grande", "latitude": 14.9768, "longitude": -23.6404, "sov_a3": "CPV", "adm0_a3": "CPV", "adm0_label": 2, "admin": "Cape Verde", "geonunit": "Cape Verde", "gu_a3": "CPV", "gn_id": 7603281, "gn_name": "Concelho de Ribeira Grande de Santiago", "gns_id": 10874225, "gns_name": "Ribeira Grande de Santiago, Concelho de", "gn_level": 1, "gn_region": "", "gn_a1_code": "CV.23", "region_sub": "", "sub_code": "", "gns_level": 1, "gns_lang": "por", "gns_adm1": "CV23", "gns_region": "", "min_label": 11, "max_label": 11, "min_zoom": 11, "wikidataid": "Q499620", "name_ar": "\u0631\u064a\u0628\u064a\u0631\u0627 \u063a\u0631\u0627\u0646\u062f\u064a \u062f\u064a \u0633\u0627\u0646\u062a\u064a\u0627\u063a\u0648\u060c \u0627\u0644\u0631\u0623\u0633 \u0627\u0644\u0623\u062e\u0636\u0631", "name_bn": "\u09b0\u0987\u09ac\u09c7\u09b0\u09be \u0997\u09cd\u09b0\u09be\u09a8\u09cd\u09a1\u09c7 \u09a6\u09bf \u09b8\u09be\u09a8\u09cd\u09a4\u09bf\u09af\u09bc\u09be\u0997\u09c1", "name_de": "Ribeira Grande de Santiago", "name_en": "Ribeira Grande de Santiago", "name_es": "Ribeira Grande de Santiago", "name_fr": "Ribeira Grande de Santiago", "name_el": "\u0394\u03ae\u03bc\u03bf\u03c2 \u03a1\u03b9\u03bc\u03c0\u03ad\u03b9\u03c1\u03b1 \u0393\u03ba\u03c1\u03ac\u03bd\u03c4\u03b5 \u03bd\u03c4\u03b5 \u03a3\u03b1\u03bd\u03c4\u03b9\u03ac\u03b3\u03bf", "name_hi": "\u0930\u093f\u092c\u0948\u0930\u093e \u0917\u094d\u0930\u0948\u0902\u0921\u0947 \u0921\u0940 \u0938\u0948\u0902\u091f\u093f\u092f\u093e\u0917\u094b", "name_hu": "", "name_id": "Ribeira Grande de Santiago", "name_it": "contea di Ribeira Grande de Santiago", "name_ja": "\u30ea\u30d9\u30a4\u30e9\u30fb\u30b0\u30e9\u30f3\u30c7\u30fb\u30c7\u30fb\u30b5\u30f3\u30c6\u30a3\u30a2\u30b4", "name_ko": "\ud788\ubca0\uc774\ub77c\uadf8\ub780\ub4dc\ub4dc\uc0b0\ud2f0\uc544\uad6c \uc2dc", "name_nl": "Ribeira Grande de Santiago", "name_pl": "Ribeira Grande de Santiago", "name_pt": "Ribeira Grande de Santiago", "name_ru": "\u0420\u0438\u0431\u0435\u0439\u0440\u0430-\u0413\u0440\u0430\u043d\u0434\u0435-\u0434\u0435-\u0421\u0430\u043d\u0442\u044c\u044f\u0433\u043e", "name_sv": "Concelho de Ribeira Grande de Santiago", "name_tr": "Ribeira Grande de Santiago", "name_vi": "Ribeira Grande de Santiago", "name_zh": "\u8056\u5730\u4e9e\u54e5\u5927\u91cc\u8c9d\u62c9\u7e23", "ne_id": 1159316327}}, {"type": "Feature", "geometry": {"type": "Polygon", "coordinates": [[[-23.471467557084946, 14.973721522596248], [-23.477894660999937, 14.96906159100007], [-23.470448370999918, 14.962225653000075], [-23.480213995999918, 14.946600653000075], [-23.486317511999914, 14.930853583000044], [-23.49400794199994, 14.91868724200009], [-23.508290167999917, 14.913804429000038], [-23.516224738999938, 14.91282786700009], [-23.531849738999938, 14.908636786000045], [-23.53929602799991, 14.907619533000059], [-23.547631118781112, 14.925713277445766], [-23.560464903032823, 14.941755507310802], [-23.564080392596054, 14.96072251053539], [-23.53639807830865, 14.966258972673415], [-23.510930349056366, 14.98286836178545], [-23.490999082841427, 14.986190238888412], [-23.471467557084946, 14.973721522596248]]]}, "properties": {"featurecla": "Admin-1 scale rank", "scalerank": 5, "adm1_code": "CPV-5053", "diss_me": 5053, "iso_3166_2": "CV-PR", "wikipedia": "http://en.wikipedia.org/wiki/Praia_(municipality)", "iso_a2": "CV", "adm0_sr": 3, "name": "Praia", "name_alt": "", "name_local": "", "type": "", "type_en": "", "code_local": "74", "code_hasc": "CV.PC", "note": "", "hasc_maybe": "", "region": "Ilhas de Sotavento", "region_cod": "CV-S", "provnum_ne": 0, "gadm_level": 0, "check_me": 0, "datarank": 10, "abbrev": "", "postal": "PR", "area_sqkm": 0, "sameascity": -99, "labelrank": 20, "name_len": 5, "mapcolor9": 4, "mapcolor13": 11, "fips": "CV14", "fips_alt": "", "woe_id": 2345125, "woe_label": "Praia, CV, Cape Verde", "woe_name": "Praia", "latitude": 14.9529, "longitude": -23.5159, "sov_a3": "CPV", "adm0_a3": "CPV", "adm0_label": 2, "admin": "Cape Verde", "geonunit": "Cape Verde", "gu_a3": "CPV", "gn_id": 3374332, "gn_name": "Concelho da Praia", "gns_id": -1313469, "gns_name": "Praia, Concelho da", "gn_level": 1, "gn_region": "", "gn_a1_code": "CV.14", "region_sub": "", "sub_code": "", "gns_level": 1, "gns_lang": "por", "gns_adm1": "CV14", "gns_region": "", "min_label": 11, "max_label": 11, "min_zoom": 11, "wikidataid": "Q497019", "name_ar": "\u0628\u0631\u0627\u064a\u0627", "name_bn": "\u09aa\u09be\u09b0\u09be\u0987\u09af\u09bc\u09be", "name_de": "Praia", "name_en": "Praia", "name_es": "Praia", "name_fr": "Praia", "name_el": "\u0394\u03ae\u03bc\u03bf\u03c2 \u03a0\u03c1\u03ac\u03b9\u03b1", "name_hi": "\u092a\u094d\u0930\u0947\u092f\u093e", "name_hu": "", "name_id": "Praia", "name_it": "contea di Praia", "name_ja": "\u30d7\u30e9\u30a4\u30a2\u5e02", "name_ko": "\ud504\ub77c\uc774\uc544 \uc2dc", "name_nl": "Praia", "name_pl": "Praia", "name_pt": "Praia", "name_ru": "\u043e\u0431\u0449\u0438\u043d\u0430 \u041f\u0440\u0430\u044f", "name_sv": "Praia", "name_tr": "Praia", "name_vi": "Praia", "name_zh": "\u666e\u62c9\u4e9e\u7e23", "ne_id": 1159316329}}, {"type": "Feature", "geometry": {"type": "Polygon", "coordinates": [[[-23.48465879678151, 15.064038365547542], [-23.470448370999918, 15.037990627000056], [-23.466542120999918, 15.03424713700008], [-23.463612433999913, 15.033148505000042], [-23.460682745999918, 15.030951239000046], [-23.456776495999918, 15.02366771000004], [-23.45457923099991, 15.018947658000059], [-23.451893683999913, 15.015122789000088], [-23.44835364499994, 15.012396552000041], [-23.443104620999918, 15.010687567000048], [-23.447824673999946, 14.995754299000055], [-23.45466061099995, 14.985907294000071], [-23.471467557084946, 14.973721522596248], [-23.490999082841427, 14.986190238888412], [-23.510930349056366, 14.98286836178545], [-23.53639807830865, 14.966258972673415], [-23.564080392596054, 14.96072251053539], [-23.58068978080877, 14.968473558607855], [-23.584011658810994, 14.995048579927982], [-23.596191876953583, 15.011657968140696], [-23.576260610738586, 15.022730894215385], [-23.56186580756099, 15.03823298946088], [-23.543041833413895, 15.053735085605695], [-23.52643244520118, 15.05927154864304], [-23.51425222705865, 15.052627793537852], [-23.50428659395118, 15.045984037533287], [-23.490999082841427, 15.051520500570632], [-23.48465879678151, 15.064038365547542]]]}, "properties": {"featurecla": "Admin-1 scale rank", "scalerank": 5, "adm1_code": "CPV-5051", "diss_me": 5051, "iso_3166_2": "CV-SD", "wikipedia": "http://en.wikipedia.org/wiki/S%C3%A3o_Domingos_(Cape_Verdean_municipality)", "iso_a2": "CV", "adm0_sr": 3, "name": "S\u00e3o Domingos", "name_alt": "", "name_local": "", "type": "", "type_en": "", "code_local": "75", "code_hasc": "CV.SD", "note": "", "hasc_maybe": "", "region": "Ilhas de Sotavento", "region_cod": "CV-S", "provnum_ne": 0, "gadm_level": 0, "check_me": 0, "datarank": 10, "abbrev": "", "postal": "SD", "area_sqkm": 0, "sameascity": -99, "labelrank": 20, "name_len": 12, "mapcolor9": 4, "mapcolor13": 11, "fips": "CV17", "fips_alt": "", "woe_id": 56051562, "woe_label": "", "woe_name": "S\u00e3o Domingos", "latitude": 15.0152, "longitude": -23.5254, "sov_a3": "CPV", "adm0_a3": "CPV", "adm0_label": 2, "admin": "Cape Verde", "geonunit": "Cape Verde", "gu_a3": "CPV", "gn_id": 3411926, "gn_name": "Concelho de Sao Domingos", "gns_id": 9146427, "gns_name": "Sao Domingos", "gn_level": 1, "gn_region": "", "gn_a1_code": "CV.17", "region_sub": "", "sub_code": "", "gns_level": 1, "gns_lang": "por", "gns_adm1": "CV17", "gns_region": "", "min_label": 11, "max_label": 11, "min_zoom": 11, "wikidataid": "Q499009", "name_ar": "\u0633\u0627\u0648 \u062f\u0648\u0645\u064a\u0646\u063a\u0648\u0633", "name_bn": "\u09b8\u09be\u0981\u0993 \u09a1\u09cb\u09ae\u09bf\u0999\u09cd\u0997\u09cb", "name_de": "S\u00e3o Domingos", "name_en": "S\u00e3o Domingos", "name_es": "S\u00e3o Domingos", "name_fr": "S\u00e3o Domingos", "name_el": "\u0394\u03ae\u03bc\u03bf\u03c2 \u03a3\u03ac\u03bf \u039d\u03c4\u03bf\u03bc\u03af\u03bd\u03b3\u03ba\u03bf\u03c2", "name_hi": "\u0938\u093e\u0913 \u0921\u094b\u092e\u093f\u0902\u0917\u094b\u0938", "name_hu": "", "name_id": "S\u00e3o Domingos", "name_it": "contea di S\u00e3o Domingos", "name_ja": "\u30b5\u30f3\u30fb\u30c9\u30df\u30f3\u30b4\u30b9", "name_ko": "\uc0c1\ub3c4\ubc0d\uad6c\uc2a4 \uc2dc", "name_nl": "S\u00e3o Domingos", "name_pl": "S\u00e3o Domingos", "name_pt": "S\u00e3o Domingos", "name_ru": "\u0421\u0430\u043d-\u0414\u043e\u043c\u0438\u043d\u0433\u043e\u0441", "name_sv": "Concelho de S\u00e3o Domingos", "name_tr": "Sao Domingos", "name_vi": "Sao Domingos", "name_zh": "\u8056\u591a\u660e\u6208\u65af\u7e23", "ne_id": 1159316323}}, {"type": "Feature", "geometry": {"type": "Polygon", "coordinates": [[[-23.5916007397357, 15.170212339067191], [-23.58421790299991, 15.16242096600007], [-23.56737219999991, 15.152085679000038], [-23.552357550999943, 15.153998114000046], [-23.54914303299995, 15.149359442000048], [-23.547474738999938, 15.14594147300005], [-23.544992641999954, 15.143133856000077], [-23.53929602799991, 15.140366929000038], [-23.540760870999918, 15.139064846000053], [-23.534413214999915, 15.133002020000049], [-23.52725175699993, 15.127386786000045], [-23.52570553299995, 15.127346096000053], [-23.52293860599991, 15.126695054000038], [-23.514068162999934, 15.12799713700008], [-23.511382615999935, 15.127346096000053], [-23.51081295499995, 15.124212958000044], [-23.51203365799995, 15.116115627000056], [-23.511382615999935, 15.113023179000038], [-23.48465879678151, 15.064038365547542], [-23.490999082841427, 15.051520500570632], [-23.50428659395118, 15.045984037533287], [-23.51425222705865, 15.052627793537852], [-23.52643244520118, 15.05927154864304], [-23.54958321329468, 15.078840620098504], [-23.564157420428614, 15.074589809871838], [-23.579976186751594, 15.08155686046075], [-23.57847519577365, 15.088061154998286], [-23.58068978080877, 15.098026788105756], [-23.607264802128896, 15.1035632511431], [-23.618337728203585, 15.105777836178163], [-23.620552313238647, 15.123494517358097], [-23.62660042127243, 15.131405931638426], [-23.620552313238647, 15.136782027568529], [-23.5916007397357, 15.170212339067191]]]}, "properties": {"featurecla": "Admin-1 scale rank", "scalerank": 5, "adm1_code": "CPV-5048", "diss_me": 5048, "iso_3166_2": "CV-CR", "wikipedia": "http://en.wikipedia.org/wiki/Santa_Cruz_(Cape_Verde)", "iso_a2": "CV", "adm0_sr": 3, "name": "Santa Cruz", "name_alt": "", "name_local": "", "type": "", "type_en": "", "code_local": "73", "code_hasc": "CV.CZ", "note": "", "hasc_maybe": "", "region": "Ilhas de Sotavento", "region_cod": "CV-S", "provnum_ne": 0, "gadm_level": 0, "check_me": 0, "datarank": 10, "abbrev": "", "postal": "CR", "area_sqkm": 0, "sameascity": -99, "labelrank": 20, "name_len": 10, "mapcolor9": 4, "mapcolor13": 11, "fips": "CV16", "fips_alt": "", "woe_id": 56051561, "woe_label": "Santa Cruz, CV, Cape Verde", "woe_name": "Santa Cruz", "latitude": 15.1157, "longitude": -23.5494, "sov_a3": "CPV", "adm0_a3": "CPV", "adm0_label": 2, "admin": "Cape Verde", "geonunit": "Cape Verde", "gu_a3": "CPV", "gn_id": 3411925, "gn_name": "Concelho de Santa Cruz", "gns_id": 9146340, "gns_name": "Santa Cruz", "gn_level": 1, "gn_region": "", "gn_a1_code": "CV.16", "region_sub": "", "sub_code": "", "gns_level": 1, "gns_lang": "por", "gns_adm1": "CV16", "gns_region": "", "min_label": 11, "max_label": 11, "min_zoom": 11, "wikidataid": "Q497472", "name_ar": "\u0633\u0627\u0646\u062a\u0627 \u0643\u0631\u0648\u0632", "name_bn": "\u09b8\u09be\u09a8\u09cd\u09a4\u09be \u0995\u09cd\u09b0\u09c1\u099c\u09c7\u09b0", "name_de": "Santa Cruz", "name_en": "Santa Cruz", "name_es": "Santa Cruz", "name_fr": "Santa Cruz", "name_el": "\u0394\u03ae\u03bc\u03bf\u03c2 \u03a3\u03ac\u03bd\u03c4\u03b1 \u039a\u03c1\u03bf\u03c5\u03b6", "name_hi": "\u0938\u093e\u0902\u0924\u093e \u0915\u094d\u0930\u0941\u091c\u093c", "name_hu": "Santa Cruz", "name_id": "Santa Cruz", "name_it": "contea di Santa Cruz", "name_ja": "\u30b5\u30f3\u30bf\u30fb\u30af\u30eb\u30b9", "name_ko": "\uc0b0\ud0c0\ud06c\ub8e8\uc2a4 \uc2dc", "name_nl": "Santa Cruz", "name_pl": "Santa Cruz", "name_pt": "Santa Cruz", "name_ru": "\u0421\u0430\u043d\u0442\u0430-\u041a\u0440\u0443\u0437", "name_sv": "Santa Cruz", "name_tr": "Santa Cruz", "name_vi": "Santa Cruz", "name_zh": "\u8056\u514b\u9b6f\u65af\u7e23", "ne_id": 1159316317}}, {"type": "Feature", "geometry": {"type": "Polygon", "coordinates": [[[-23.656076626999948, 15.229722398000092], [-23.638783331999946, 15.226263739000046], [-23.63027910099993, 15.219183661000045], [-23.61510169199994, 15.195013739000046], [-23.5916007397357, 15.170212339067191], [-23.620552313238647, 15.136782027568529], [-23.62660042127243, 15.131405931638426], [-23.640483579453644, 15.119065347287915], [-23.64823462752605, 15.121279932322977], [-23.650449212561114, 15.136782027568529], [-23.66816589374099, 15.148962246610381], [-23.686989866988768, 15.166678926890938], [-23.685882574920925, 15.184395608070815], [-23.670380478776053, 15.206541459320874], [-23.656076626999948, 15.229722398000092]]]}, "properties": {"featurecla": "Admin-1 scale rank", "scalerank": 5, "adm1_code": "CPV-5047", "diss_me": 5047, "iso_3166_2": "CV-SM", "wikipedia": "http://en.wikipedia.org/wiki/S%C3%A3o_Miguel_(Cape_Verde)", "iso_a2": "CV", "adm0_sr": 3, "name": "S\u00e3o Miguel", "name_alt": "", "name_local": "", "type": "", "type_en": "", "code_local": "76", "code_hasc": "CV.SM", "note": "", "hasc_maybe": "", "region": "Ilhas de Sotavento", "region_cod": "CV-S", "provnum_ne": 0, "gadm_level": 0, "check_me": 0, "datarank": 10, "abbrev": "", "postal": "SM", "area_sqkm": 0, "sameascity": -99, "labelrank": 20, "name_len": 10, "mapcolor9": 4, "mapcolor13": 11, "fips": "CV19", "fips_alt": "", "woe_id": 56051558, "woe_label": "S\u00c3\u00a3o Miguel, CV, Cape Verde", "woe_name": "S\u00c3\u00a3o Miguel", "latitude": 15.178, "longitude": -23.6356, "sov_a3": "CPV", "adm0_a3": "CPV", "adm0_label": 2, "admin": "Cape Verde", "geonunit": "Cape Verde", "gu_a3": "CPV", "gn_id": 3411928, "gn_name": "Concelho de Sao Miguel", "gns_id": 9146436, "gns_name": "Sao Miguel", "gn_level": 1, "gn_region": "", "gn_a1_code": "CV.19", "region_sub": "", "sub_code": "", "gns_level": 1, "gns_lang": "por", "gns_adm1": "CV19", "gns_region": "", "min_label": 11, "max_label": 11, "min_zoom": 11, "wikidataid": "Q494874", "name_ar": "", "name_bn": "", "name_de": "S\u00e3o Miguel", "name_en": "S\u00e3o Miguel", "name_es": "S\u00e3o Miguel", "name_fr": "S\u00e3o Miguel", "name_el": "", "name_hi": "", "name_hu": "", "name_id": "", "name_it": "contea di S\u00e3o Miguel", "name_ja": "\u30b5\u30f3\u30fb\u30df\u30b2\u30eb", "name_ko": "\uc0c1\ubbf8\uac94 \uc2dc", "name_nl": "S\u00e3o Miguel", "name_pl": "S\u00e3o Miguel", "name_pt": "S\u00e3o Miguel", "name_ru": "", "name_sv": "", "name_tr": "", "name_vi": "", "name_zh": "\u8056\u7c73\u6208\u723e\u7e23", "ne_id": 1159316315}}, {"type": "Feature", "geometry": {"type": "Polygon", "coordinates": [[[-23.127797003999945, 15.311672268000052], [-23.121896938999953, 15.29913971600007], [-23.12051347599993, 15.283351955000057], [-23.121571417999917, 15.256415106000077], [-23.11046301999994, 15.199408270000049], [-23.111927863999938, 15.171942450000074], [-23.127797003999945, 15.146633205000057], [-23.132801886999914, 15.144720770000049], [-23.14867102799991, 15.142767645000049], [-23.155140753999945, 15.140366929000038], [-23.15884355399993, 15.135565497000073], [-23.16364498599995, 15.123724677000041], [-23.168812628999945, 15.11985911700009], [-23.18272864499994, 15.11859772300005], [-23.19595292899993, 15.12205638200004], [-23.217152472999942, 15.13353099200009], [-23.240630662999934, 15.150051174000055], [-23.252064581999946, 15.161810614000046], [-23.258168097999942, 15.174505927000041], [-23.255116339999915, 15.186835028000075], [-23.247303839999915, 15.19920482000009], [-23.24327551999994, 15.211330471000053], [-23.251332160999937, 15.22288646000004], [-23.237172003999945, 15.231024481000077], [-23.230865037999934, 15.243963934000078], [-23.234852667999917, 15.254828192000048], [-23.251332160999937, 15.256415106000077], [-23.245716925999943, 15.271063544000071], [-23.22411048099991, 15.286688544000071], [-23.209787563999953, 15.311672268000052], [-23.214466925999943, 15.31354401200008], [-23.21515865799995, 15.31443919500009], [-23.214955206999946, 15.315822658000059], [-23.217152472999942, 15.319159247000073], [-23.203277147999927, 15.324896552000041], [-23.189849412999934, 15.33274974200009], [-23.189564581999946, 15.329494533000059], [-23.189849412999934, 15.319159247000073], [-23.181263800999943, 15.325751044000071], [-23.178944464999915, 15.327948309000078], [-23.176258917999917, 15.33274974200009], [-23.168812628999945, 15.325344143000052], [-23.176258917999917, 15.319159247000073], [-23.161936001999948, 15.312567450000074], [-23.139515753999945, 15.317775783000059], [-23.127797003999945, 15.311672268000052]]]}, "properties": {"featurecla": "Admin-1 scale rank", "scalerank": 5, "adm1_code": "CPV-5054", "diss_me": 5054, "iso_3166_2": "CV-MA", "wikipedia": "http://en.wikipedia.org/wiki/Maio_(Cape_Verde)", "iso_a2": "CV", "adm0_sr": 3, "name": "Maio", "name_alt": "", "name_local": "", "type": "", "type_en": "", "code_local": "61", "code_hasc": "CV.MA", "note": "", "hasc_maybe": "", "region": "Ilhas de Sotavento", "region_cod": "CV-S", "provnum_ne": 0, "gadm_level": 0, "check_me": 0, "datarank": 10, "abbrev": "", "postal": "MA", "area_sqkm": 0, "sameascity": -99, "labelrank": 20, "name_len": 4, "mapcolor9": 4, "mapcolor13": 11, "fips": "CV04", "fips_alt": "", "woe_id": 2345124, "woe_label": "Maio, CV, Cape Verde", "woe_name": "Maio", "latitude": 15.2115, "longitude": -23.1806, "sov_a3": "CPV", "adm0_a3": "CPV", "adm0_label": 2, "admin": "Cape Verde", "geonunit": "Cape Verde", "gu_a3": "CPV", "gn_id": 3374487, "gn_name": "Concelho do Maio", "gns_id": -1313314, "gns_name": "Maio", "gn_level": 1, "gn_region": "", "gn_a1_code": "CV.04", "region_sub": "", "sub_code": "", "gns_level": 1, "gns_lang": "por", "gns_adm1": "CV04", "gns_region": "", "min_label": 11, "max_label": 11, "min_zoom": 11, "wikidataid": "Q2551133", "name_ar": "", "name_bn": "", "name_de": "Maio", "name_en": "Maio", "name_es": "Maio", "name_fr": "Maio", "name_el": "", "name_hi": "", "name_hu": "", "name_id": "", "name_it": "contea di Maio", "name_ja": "\u30de\u30a4\u30aa", "name_ko": "\ub9c8\uc774\uc6b0 \uc2dc", "name_nl": "Maio", "name_pl": "", "name_pt": "Maio", "name_ru": "", "name_sv": "", "name_tr": "", "name_vi": "", "name_zh": "\u99ac\u7d04\u5cf6\u7e23", "ne_id": 1159316331}}, {"type": "Feature", "geometry": {"type": "Polygon", "coordinates": [[[-22.682118292999917, 16.11359284100007], [-22.67837480399993, 16.111883856000077], [-22.670806443999936, 16.10224030200004], [-22.666574673999946, 16.091457424000055], [-22.67251542899993, 16.086330471000053], [-22.675607876999948, 16.08201732000009], [-22.677113410999937, 16.072658596000053], [-22.679798956999946, 16.06321849200009], [-22.696441209999932, 16.05292389500005], [-22.75108801999994, 16.010565497000073], [-22.787587042999917, 15.991603908000059], [-22.80614173099991, 15.985907294000071], [-22.863677537999934, 15.982367255000042], [-22.873890753999945, 15.983872789000088], [-22.883656378999945, 15.988714911000045], [-22.897775844999956, 16.000474351000037], [-22.90929114499994, 16.003729559000078], [-22.94554602799991, 16.019680080000057], [-22.957753058999913, 16.03082916900007], [-22.96397864499994, 16.05219147300005], [-22.963246222999942, 16.071193752000056], [-22.957753058999913, 16.089016018000052], [-22.947417772999927, 16.10224030200004], [-22.93260657499991, 16.10740794500009], [-22.91356360599991, 16.125555731000077], [-22.924427863999938, 16.212958075000074], [-22.91559811099995, 16.243963934000078], [-22.91161048099991, 16.236721096000053], [-22.90721594999991, 16.23143138200004], [-22.895090298999946, 16.22284577000005], [-22.87791907499991, 16.214911200000074], [-22.85252844999991, 16.20661041900007], [-22.829416469999956, 16.204006252000056], [-22.81932532499991, 16.212958075000074], [-22.811675584999932, 16.22842031500005], [-22.793812628999945, 16.231350002000056], [-22.73468990799995, 16.216864325000074], [-22.723866339999915, 16.212632554000038], [-22.71385657499991, 16.20575592700004], [-22.709828253999945, 16.19863515800006], [-22.70376542899993, 16.17959219000005], [-22.699574347999942, 16.17568594000005], [-22.682484503999945, 16.16864655200004], [-22.67870032499991, 16.15176015800006], [-22.682118292999917, 16.11359284100007]]]}, "properties": {"featurecla": "Admin-1 scale rank", "scalerank": 5, "adm1_code": "CPV-5055", "diss_me": 5055, "iso_3166_2": "CV-BV", "wikipedia": "http://en.wikipedia.org/wiki/Boa_Vista_(Cape_Verde)", "iso_a2": "CV", "adm0_sr": 3, "name": "Boa Vista", "name_alt": "", "name_local": "", "type": "", "type_en": "", "code_local": "51", "code_hasc": "CV.BV", "note": "", "hasc_maybe": "", "region": "Ilhas de Barlavento", "region_cod": "CV-B", "provnum_ne": 0, "gadm_level": 0, "check_me": 0, "datarank": 10, "abbrev": "", "postal": "", "area_sqkm": 0, "sameascity": -99, "labelrank": 20, "name_len": 9, "mapcolor9": 4, "mapcolor13": 11, "fips": "CV01", "fips_alt": "", "woe_id": 2345121, "woe_label": "Boa Vista, CV, Cape Verde", "woe_name": "Boa Vista", "latitude": 16.1024, "longitude": -22.807, "sov_a3": "CPV", "adm0_a3": "CPV", "adm0_label": 2, "admin": "Cape Verde", "geonunit": "Cape Verde", "gu_a3": "CPV", "gn_id": 3374855, "gn_name": "Concelho da Boa Vista", "gns_id": -1312946, "gns_name": "Boa Vista", "gn_level": 1, "gn_region": "", "gn_a1_code": "CV.01", "region_sub": "", "sub_code": "", "gns_level": 1, "gns_lang": "por", "gns_adm1": "CV01", "gns_region": "", "min_label": 11, "max_label": 11, "min_zoom": 11, "wikidataid": "Q2721025", "name_ar": "\u0628\u0648\u0627 \u0641\u064a\u0633\u062a\u0627", "name_bn": "\u09ac\u09c1\u09af\u09bc\u09cb \u09ad\u09bf\u09b8\u09cd\u09a4\u09be", "name_de": "Boa Vista", "name_en": "Boa Vista", "name_es": "Boavista", "name_fr": "Boa Vista", "name_el": "\u0394\u03ae\u03bc\u03bf\u03c2 \u039c\u03c0\u03cc\u03b1 \u0392\u03af\u03c3\u03c4\u03b1", "name_hi": "\u092c\u094b\u0906 \u0935\u093f\u0938\u094d\u091f\u093e", "name_hu": "", "name_id": "Boa Vista", "name_it": "contea di Boa Vista", "name_ja": "\u30dc\u30a2\u30fb\u30f4\u30a3\u30b9\u30bf", "name_ko": "\ubcf4\uc544\ube44\uc2a4\ud0c0 \uc2dc", "name_nl": "Boa Vista", "name_pl": "Boa Vista", "name_pt": "Boa Vista", "name_ru": "\u0411\u043e\u0430-\u0412\u0438\u0441\u0442\u0430", "name_sv": "Boa Vista", "name_tr": "Boa Vista", "name_vi": "Boa Vista", "name_zh": "\u535a\u963f\u7dad\u65af\u5854\u5cf6\u7e23", "ne_id": 1159316333}}, {"type": "Feature", "geometry": {"type": "Polygon", "coordinates": [[[-24.37562265594058, 16.677122962535748], [-24.361480272999927, 16.681586005000042], [-24.354237433999913, 16.680609442000048], [-24.340565558999913, 16.67536041900007], [-24.328684048999946, 16.667792059000078], [-24.305165167999917, 16.64789459800005], [-24.29283606699994, 16.641831773000092], [-24.282378709999932, 16.64134349200009], [-24.22679602799991, 16.649603583000044], [-24.21711178299995, 16.647691148000092], [-24.180572068999936, 16.63084544500009], [-24.172474738999938, 16.62909577000005], [-24.089995897999927, 16.62246328300006], [-24.067534959999932, 16.61391836100006], [-24.04796301999994, 16.598822333000044], [-24.03742428299995, 16.593003648000092], [-24.032826300999943, 16.596828518000052], [-24.032826300999943, 16.56240469000005], [-24.044097459999932, 16.559881903000075], [-24.11473548099991, 16.55927155200004], [-24.191965298999946, 16.59247467700004], [-24.233306443999936, 16.602118231000077], [-24.272328253999945, 16.587225653000075], [-24.286366339999915, 16.570746161000045], [-24.315337693999936, 16.520412502000056], [-24.324696417999917, 16.48265208500004], [-24.326013104121444, 16.512572117908917], [-24.320215463572765, 16.554812071120182], [-24.314417823024144, 16.581315571156665], [-24.320215463572765, 16.61278847660691], [-24.338436620353775, 16.627696695546035], [-24.366596588861512, 16.62935316491661], [-24.376535401487615, 16.64260491448522], [-24.366596588861512, 16.655856664053772], [-24.37562265594058, 16.677122962535748]]]}, "properties": {"featurecla": "Admin-1 scale rank", "scalerank": 5, "adm1_code": "CPV-5057", "diss_me": 5057, "iso_3166_2": "CV-RB", "wikipedia": "http://en.wikipedia.org/wiki/Ribeira_Brava_(municipality)", "iso_a2": "CV", "adm0_sr": 3, "name": "Ribeira Brava", "name_alt": "", "name_local": "", "type": "", "type_en": "", "code_local": "31", "code_hasc": "CV.RB", "note": "", "hasc_maybe": "", "region": "Ilhas de Barlavento", "region_cod": "CV-B", "provnum_ne": 0, "gadm_level": 0, "check_me": 0, "datarank": 10, "abbrev": "", "postal": "", "area_sqkm": 0, "sameascity": -99, "labelrank": 20, "name_len": 13, "mapcolor9": 4, "mapcolor13": 11, "fips": "CV22", "fips_alt": "", "woe_id": 56051567, "woe_label": "Ribeira Brava, CV, Cape Verde", "woe_name": "Ribeira Brava", "latitude": 16.6197, "longitude": -24.287, "sov_a3": "CPV", "adm0_a3": "CPV", "adm0_label": 2, "admin": "Cape Verde", "geonunit": "Cape Verde", "gu_a3": "CPV", "gn_id": 7602869, "gn_name": "Concelho da Ribeira Brava", "gns_id": 10872167, "gns_name": "Ribeira Brava, Concelho da", "gn_level": 1, "gn_region": "", "gn_a1_code": "CV.22", "region_sub": "", "sub_code": "", "gns_level": 1, "gns_lang": "por", "gns_adm1": "CV22", "gns_region": "", "min_label": 11, "max_label": 11, "min_zoom": 11, "wikidataid": "Q747221", "name_ar": "\u0631\u064a\u0628\u064a\u0631\u0627 \u0628\u0631\u0627\u0641\u0627", "name_bn": "\u09b0\u09bf\u09ac\u09c7\u0987\u09b0\u09be \u09ac\u09cd\u09b0\u09be\u09ad\u09be", "name_de": "Ribeira Brava", "name_en": "Ribeira Brava", "name_es": "Ribeira Brava", "name_fr": "Ribeira Brava", "name_el": "\u0394\u03ae\u03bc\u03bf\u03c2 \u03a1\u03b9\u03bc\u03c0\u03ad\u03b9\u03c1\u03b1 \u039c\u03c0\u03c1\u03ac\u03b2\u03b1", "name_hi": "\u0930\u093f\u092c\u0947\u0930\u093e \u092c\u094d\u0930\u093e\u0935\u093e", "name_hu": "", "name_id": "Ribeira Brava", "name_it": "contea di Ribeira Brava", "name_ja": "\u30ea\u30d9\u30a4\u30e9\u30fb\u30d6\u30e9\u30f4\u30a1", "name_ko": "\ud788\ubca0\uc774\ub77c\ube0c\ub77c\ubc14 \uc2dc", "name_nl": "Ribeira Brava", "name_pl": "Ribeira Brava", "name_pt": "Ribeira Brava", "name_ru": "\u0420\u0438\u0431\u0435\u0439\u0440\u0430-\u0411\u0440\u0430\u0432\u0430", "name_sv": "Concelho da Ribeira Brava", "name_tr": "Ribeira Brava", "name_vi": "Ribeira Brava", "name_zh": "\u91cc\u8c9d\u62c9\u5e03\u62c9\u74e6\u7e23", "ne_id": 1159316337}}, {"type": "Feature", "geometry": {"type": "Polygon", "coordinates": [[[-24.324696417999917, 16.48265208500004], [-24.33340410099993, 16.494940497000073], [-24.347482876999948, 16.53196849200009], [-24.35338294199994, 16.54043203300006], [-24.360178188999953, 16.54718659100007], [-24.365630662999934, 16.555609442000048], [-24.367909308999913, 16.569159247000073], [-24.36856035099993, 16.57953522300005], [-24.370920376999948, 16.587144273000092], [-24.37608801999994, 16.59178294500009], [-24.38508053299995, 16.593410549000055], [-24.408273891999954, 16.600165106000077], [-24.424712693999936, 16.617132880000042], [-24.43065344999991, 16.639471747000073], [-24.422596808999913, 16.66229889500005], [-24.37562265594058, 16.677122962535748], [-24.366596588861512, 16.655856664053772], [-24.376535401487615, 16.64260491448522], [-24.366596588861512, 16.62935316491661], [-24.338436620353775, 16.627696695546035], [-24.320215463572765, 16.61278847660691], [-24.314417823024144, 16.581315571156665], [-24.320215463572765, 16.554812071120182], [-24.326013104121444, 16.512572117908917], [-24.324696417999917, 16.48265208500004]]]}, "properties": {"featurecla": "Admin-1 scale rank", "scalerank": 5, "adm1_code": "CPV-5058", "diss_me": 5058, "iso_3166_2": "CV-TS", "wikipedia": "http://en.wikipedia.org/wiki/Tarrafal_de_S%C3%A3o_Nicolau_(municipality)", "iso_a2": "CV", "adm0_sr": 3, "name": "Tarrafal de S\u00e3o Nicolau", "name_alt": "", "name_local": "", "type": "", "type_en": "", "code_local": "31", "code_hasc": "CV.TS", "note": "", "hasc_maybe": "", "region": "Ilhas de Barlavento", "region_cod": "CV-B", "provnum_ne": 0, "gadm_level": 0, "check_me": 0, "datarank": 10, "abbrev": "", "postal": "", "area_sqkm": 0, "sameascity": -99, "labelrank": 20, "name_len": 23, "mapcolor9": 4, "mapcolor13": 11, "fips": "CV27", "fips_alt": "", "woe_id": 2345129, "woe_label": "Tarrafal de S\u00c3\u00a3o Nicolau, CV, Cape Verde", "woe_name": "Tarrafal de S\u00c3\u00a3o Nicolau", "latitude": 16.6006, "longitude": -24.3493, "sov_a3": "CPV", "adm0_a3": "CPV", "adm0_label": 2, "admin": "Cape Verde", "geonunit": "Cape Verde", "gu_a3": "CPV", "gn_id": 7602872, "gn_name": "Concelho do Tarrafal de Sao Nicolau", "gns_id": 10874254, "gns_name": "Tarrafal de Sao Nicolau, Concelho do", "gn_level": 1, "gn_region": "", "gn_a1_code": "CV.27", "region_sub": "", "sub_code": "", "gns_level": 1, "gns_lang": "por", "gns_adm1": "CV27", "gns_region": "", "min_label": 11, "max_label": 11, "min_zoom": 11, "wikidataid": "Q1895853", "name_ar": "\u062a\u0627\u0631\u0641\u0627\u0644 \u062f\u064a \u0633\u0627\u0648 \u0646\u064a\u0643\u0648\u0644\u0627\u0648", "name_bn": "\u09a4\u09cd\u09b0\u09b0\u09be\u09ab\u09be\u09b2 \u09a6\u09c7 \u09b8\u09be\u0993 \u09a8\u09bf\u0995\u09cb\u09b2\u09be\u0989", "name_de": "Tarrafal de S\u00e3o Nicolau", "name_en": "Tarrafal de S\u00e3o Nicolau", "name_es": "Tarrafal de S\u00e3o Nicolau", "name_fr": "Tarrafal de S\u00e3o Nicolau", "name_el": "\u0394\u03ae\u03bc\u03bf\u03c2 \u03a4\u03b1\u03c1\u03c1\u03b1\u03c6\u03ac\u03bb \u03bd\u03c4\u03b5 \u03a3\u03ac\u03bf \u039d\u03b9\u03ba\u03bf\u03bb\u03ac\u03bf\u03c5", "name_hi": "\u0924\u0930\u093e\u092b\u0932 \u0921\u0947 \u0938\u093e\u0913 \u0928\u093f\u0915\u094b\u0932\u094c", "name_hu": "", "name_id": "Tarrafal de S\u00e3o Nicolau", "name_it": "contea di Tarrafal de S\u00e3o Nicolau", "name_ja": "\u30bf\u30e9\u30d5\u30a1\u30eb\u30fb\u30c7\u30fb\u30b5\u30f3\u30fb\u30cb\u30b3\u30e9\u30a6", "name_ko": "\ud0c0\ud558\ud314\ub4dc\uc0c1\ub2c8\ucf5c\ub77c\uc6b0 \uc2dc", "name_nl": "Tarrafal de S\u00e3o Nicolau", "name_pl": "Tarrafal de S\u00e3o Nicolau", "name_pt": "Tarrafal de S\u00e3o Nicolau", "name_ru": "\u0422\u0430\u0440\u0440\u0430\u0444\u0430\u043b-\u0434\u0435-\u0421\u0430\u043d-\u041d\u0438\u043a\u043e\u043b\u0430\u0443", "name_sv": "Tarrafal de S\u00e3o Nicolau", "name_tr": "Tarrafal de Sao Belediyesi", "name_vi": "Tarrafal de Sao Nicolau", "name_zh": "\u8056\u5c3c\u53e4\u52de\u5854\u62c9\u6cd5\u723e\u7e23", "ne_id": 1159316339}}, {"type": "Feature", "geometry": {"type": "Polygon", "coordinates": [[[-22.92918860599991, 16.593410549000055], [-22.941395636999914, 16.66937897300005], [-22.95653235599991, 16.69944896000004], [-22.97760982999995, 16.68903229400007], [-22.981760219999956, 16.703517971000053], [-22.983143683999913, 16.723049221000053], [-22.98005123599995, 16.741115627000056], [-22.970814581999946, 16.75104401200008], [-22.970814581999946, 16.757879950000074], [-22.98273678299995, 16.761379299000055], [-22.98924719999991, 16.77094147300005], [-22.991566535999937, 16.784328518000052], [-22.990793423999946, 16.815659898000092], [-22.97012285099993, 16.83144765800006], [-22.922434048999946, 16.860296942000048], [-22.91698157499991, 16.853176174000055], [-22.898915167999917, 16.836818752000056], [-22.895090298999946, 16.829291083000044], [-22.896311001999948, 16.825018622000073], [-22.902740037999934, 16.81317780200004], [-22.909779425999943, 16.80337148600006], [-22.907948370999918, 16.800604559000078], [-22.904042120999918, 16.798570054000038], [-22.90184485599991, 16.79511139500005], [-22.904652472999942, 16.73582591400009], [-22.90184485599991, 16.716945705000057], [-22.897368943999936, 16.710272528000075], [-22.88418535099993, 16.698431708000044], [-22.881337042999917, 16.692694403000075], [-22.88239498599995, 16.68154531500005], [-22.88662675699993, 16.66168854400007], [-22.887603318999936, 16.65143463700008], [-22.889556443999936, 16.64590078300006], [-22.898793097999942, 16.639471747000073], [-22.90184485599991, 16.634426174000055], [-22.90147864499994, 16.62909577000005], [-22.89940344999991, 16.621649481000077], [-22.896839972999942, 16.61546458500004], [-22.895090298999946, 16.61391836100006], [-22.901722785999937, 16.605902411000045], [-22.90884355399993, 16.60219961100006], [-22.917632615999935, 16.59918854400007], [-22.92918860599991, 16.593410549000055]]]}, "properties": {"featurecla": "Admin-1 scale rank", "scalerank": 5, "adm1_code": "CPV-5056", "diss_me": 5056, "iso_3166_2": "CV-SL", "wikipedia": "http://en.wikipedia.org/wiki/Sal_(Cape_Verde)", "iso_a2": "CV", "adm0_sr": 3, "name": "Sal", "name_alt": "", "name_local": "", "type": "", "type_en": "", "code_local": "41", "code_hasc": "CV.SL", "note": "", "hasc_maybe": "", "region": "Ilhas de Barlavento", "region_cod": "CV-B", "provnum_ne": 0, "gadm_level": 0, "check_me": 0, "datarank": 10, "abbrev": "", "postal": "", "area_sqkm": 0, "sameascity": -99, "labelrank": 20, "name_len": 3, "mapcolor9": 4, "mapcolor13": 11, "fips": "CV08", "fips_alt": "", "woe_id": 2345127, "woe_label": "Sal, CV, Cape Verde", "woe_name": "Sal", "latitude": 16.7251, "longitude": -22.9363, "sov_a3": "CPV", "adm0_a3": "CPV", "adm0_label": 2, "admin": "Cape Verde", "geonunit": "Cape Verde", "gu_a3": "CPV", "gn_id": 3374249, "gn_name": "Concelho do Sal", "gns_id": -1313552, "gns_name": "Sal", "gn_level": 1, "gn_region": "", "gn_a1_code": "CV.08", "region_sub": "", "sub_code": "", "gns_level": 1, "gns_lang": "por", "gns_adm1": "CV08", "gns_region": "", "min_label": 11, "max_label": 11, "min_zoom": 11, "wikidataid": "Q2721003", "name_ar": "\u0633\u0627\u0644", "name_bn": "\u09b8\u09be\u09b2", "name_de": "Sal", "name_en": "Sal", "name_es": "Sal", "name_fr": "Sal", "name_el": "\u0394\u03ae\u03bc\u03bf\u03c2 \u03a3\u03b1\u03bb", "name_hi": "\u0938\u093e\u0932", "name_hu": "Sal", "name_id": "Sal", "name_it": "contea di Sal", "name_ja": "\u30b5\u30eb", "name_ko": "\uc0b4 \uc2dc", "name_nl": "Sal", "name_pl": "Sal", "name_pt": "Sal", "name_ru": "\u0421\u0430\u043b", "name_sv": "Sal", "name_tr": "Sal", "name_vi": "Sal", "name_zh": "\u85a9\u723e\u7e23", "ne_id": 1159316335}}, {"type": "Feature", "geometry": {"type": "MultiPolygon", "coordinates": [[[[-24.919748501999948, 16.895086981000077], [-24.92292232999995, 16.89081452000005], [-24.914458787999934, 16.881415106000077], [-24.900135870999918, 16.872015692000048], [-24.885894334999932, 16.867743231000077], [-24.88109290299991, 16.86229075700004], [-24.876291469999956, 16.84983958500004], [-24.873605923999946, 16.83592357000009], [-24.875070766999954, 16.82615794500009], [-24.891102667999917, 16.81395091400009], [-24.91551673099991, 16.805487372000073], [-24.94286048099991, 16.800482489000046], [-24.968129035999937, 16.798895575000074], [-24.97451738199993, 16.796698309000078], [-24.984201626999948, 16.78733958500004], [-24.988026495999918, 16.78514232000009], [-24.99522864499994, 16.78611888200004], [-25.05817623599995, 16.80963776200008], [-25.06822669199994, 16.81509023600006], [-25.076161261999914, 16.82245514500005], [-25.08112545499995, 16.83234284100007], [-25.094146287999934, 16.82615794500009], [-25.08975175699993, 16.847479559000078], [-25.078195766999954, 16.865057684000078], [-25.06358801999994, 16.877020575000074], [-25.050119594999956, 16.881415106000077], [-25.018788214999915, 16.882025458000044], [-25.005970831999946, 16.88768138200004], [-25.012196417999917, 16.901271877000056], [-24.983998175999943, 16.915961005000042], [-24.97809811099995, 16.923000393000052], [-24.971262173999946, 16.923000393000052], [-24.965199347999942, 16.90892161700009], [-24.955189581999946, 16.91079336100006], [-24.93773352799991, 16.923000393000052], [-24.927723761999914, 16.917792059000078], [-24.918771938999953, 16.908270575000074], [-24.91470292899993, 16.89915599200009], [-24.919748501999948, 16.895086981000077]]], [[[-24.592659601036317, 16.624312420871888], [-24.569512031034343, 16.61997225149652], [-24.575298923534838, 16.605505020245285], [-24.58976615478607, 16.60695174337041], [-24.601339939787056, 16.609845189620657], [-24.604233386037304, 16.621418974621644], [-24.592659601036317, 16.624312420871888]]], [[[-24.773499991676733, 16.80225936526206], [-24.74890569854964, 16.79357902651132], [-24.735885190423527, 16.779111795260086], [-24.725758128547664, 16.757410948383235], [-24.70695072792106, 16.753070779007867], [-24.695376942920074, 16.760304394633483], [-24.683803157919087, 16.75596422525811], [-24.68524988104421, 16.742943717132004], [-24.70261055854569, 16.735710101506385], [-24.722864682297416, 16.73426337838126], [-24.740225359798895, 16.73426337838126], [-24.74890569854964, 16.742943717132004], [-24.75469259105013, 16.754517502132988], [-24.773499991676733, 16.761751117758607], [-24.787967222927968, 16.774771625884714], [-24.787967222927968, 16.78923885713595], [-24.773499991676733, 16.80225936526206]]]]}, "properties": {"featurecla": "Admin-1 scale rank", "scalerank": 5, "adm1_code": "CPV-5059", "diss_me": 5059, "iso_3166_2": "CV-SV", "wikipedia": "http://en.wikipedia.org/wiki/S%C3%A3o_Vicente,_Cape_Verde_(municipality)", "iso_a2": "CV", "adm0_sr": 3, "name": "S\u00e3o Vicente", "name_alt": "", "name_local": "", "type": "", "type_en": "", "code_local": "21", "code_hasc": "CV.SV", "note": "", "hasc_maybe": "", "region": "Ilhas de Barlavento", "region_cod": "CV-B", "provnum_ne": 0, "gadm_level": 0, "check_me": 0, "datarank": 10, "abbrev": "", "postal": "", "area_sqkm": 0, "sameascity": -99, "labelrank": 20, "name_len": 11, "mapcolor9": 4, "mapcolor13": 11, "fips": "CV11", "fips_alt": "", "woe_id": 2345130, "woe_label": "S\u00c3\u00a3o Vicente, CV, Cape Verde", "woe_name": "S\u00c3\u00a3o Vicente", "latitude": 16.8449, "longitude": -24.972, "sov_a3": "CPV", "adm0_a3": "CPV", "adm0_label": 2, "admin": "Cape Verde", "geonunit": "Cape Verde", "gu_a3": "CPV", "gn_id": 3374198, "gn_name": "Concelho de Sao Vicente", "gns_id": -1313603, "gns_name": "Sao Vicente", "gn_level": 1, "gn_region": "", "gn_a1_code": "CV.11", "region_sub": "", "sub_code": "", "gns_level": 1, "gns_lang": "por", "gns_adm1": "CV11", "gns_region": "", "min_label": 11, "max_label": 11, "min_zoom": 11, "wikidataid": "Q648842", "name_ar": "\u0633\u0627\u0648 \u0641\u064a\u0633\u0646\u062a\u064a", "name_bn": "\u09b8\u09be\u0981\u0993 \u09ad\u09bf\u09a8\u09cd\u09b8\u09c7\u09a8\u09cd\u099f", "name_de": "S\u00e3o Vicente", "name_en": "S\u00e3o Vicente", "name_es": "S\u00e3o Vicente", "name_fr": "S\u00e3o Vicente", "name_el": "\u0394\u03ae\u03bc\u03bf\u03c2 \u03a3\u03ac\u03bf \u0392\u03b9\u03c3\u03ad\u03bd\u03c4\u03b5", "name_hi": "\u0938\u093e\u0913 \u0935\u093f\u0938\u0947\u0902\u091f\u0947", "name_hu": "", "name_id": "S\u00e3o Vicente", "name_it": "contea di S\u00e3o Vicente", "name_ja": "\u30b5\u30f3\u30fb\u30d3\u30bb\u30f3\u30c6", "name_ko": "\uc0c1\ube44\uc13c\ud2b8 \uc2dc", "name_nl": "S\u00e3o Vicente", "name_pl": "S\u00e3o Vicente", "name_pt": "S\u00e3o Vicente", "name_ru": "\u0421\u0430\u043d-\u0412\u0438\u0441\u0435\u043d\u0442\u0438", "name_sv": "S\u00e3o Vicente", "name_tr": "Sao Vicente", "name_vi": "Sao Vicente", "name_zh": "\u8056\u7dad\u68ee\u7279\u7e23", "ne_id": 1159316341}}, {"type": "Feature", "geometry": {"type": "Polygon", "coordinates": [[[-25.245350715263328, 17.136704820371165], [-25.226307745999918, 17.144680080000057], [-25.20270748599995, 17.158758856000077], [-25.17955481699994, 17.16437409100007], [-25.11864173099991, 17.19285716400009], [-25.10260982999995, 17.196600653000075], [-25.091053839999915, 17.193019924000055], [-25.07949785099993, 17.185370184000078], [-25.053944464999915, 17.18618398600006], [-25.039540167999917, 17.182440497000073], [-25.030181443999936, 17.175482489000046], [-25.026275193999936, 17.167710679000038], [-25.025868292999917, 17.144924221000053], [-25.038245774722725, 17.138367811625187], [-25.054122508646856, 17.127452556490255], [-25.072976131643145, 17.113560413182483], [-25.11266796735282, 17.103637454704767], [-25.158313579408173, 17.085776128365637], [-25.191059344812913, 17.107606637736126], [-25.245350715263328, 17.136704820371165]]]}, "properties": {"featurecla": "Admin-1 scale rank", "scalerank": 5, "adm1_code": "CPV-5061", "diss_me": 5061, "iso_3166_2": "CV-RG", "wikipedia": "http://en.wikipedia.org/wiki/Ribeira_Grande_(Cape_Verdean_municipality)", "iso_a2": "CV", "adm0_sr": 3, "name": "Ribeira Grande", "name_alt": "", "name_local": "", "type": "", "type_en": "", "code_local": "11", "code_hasc": "CV.RG", "note": "", "hasc_maybe": "", "region": "Ilhas de Barlavento", "region_cod": "CV-B", "provnum_ne": 0, "gadm_level": 0, "check_me": 0, "datarank": 10, "abbrev": "", "postal": "", "area_sqkm": 0, "sameascity": -99, "labelrank": 20, "name_len": 14, "mapcolor9": 4, "mapcolor13": 11, "fips": "CV07", "fips_alt": "", "woe_id": 2345126, "woe_label": "Ribeira Grande, CV, Cape Verde", "woe_name": "Ribeira Grande", "latitude": 17.1418, "longitude": -25.1204, "sov_a3": "CPV", "adm0_a3": "CPV", "adm0_label": 2, "admin": "Cape Verde", "geonunit": "Cape Verde", "gu_a3": "CPV", "gn_id": 3374274, "gn_name": "Concelho da Ribeira Grande", "gns_id": -1313527, "gns_name": "Ribeira Grande, Concelho da", "gn_level": 1, "gn_region": "", "gn_a1_code": "CV.07", "region_sub": "", "sub_code": "", "gns_level": 1, "gns_lang": "por", "gns_adm1": "CV07", "gns_region": "", "min_label": 11, "max_label": 11, "min_zoom": 11, "wikidataid": "Q1355642", "name_ar": "\u0631\u064a\u0628\u064a\u0631\u0627 \u063a\u0631\u0627\u0646\u062f\u064a", "name_bn": "\u09b0\u09ac\u09bf\u09b0\u09be \u0997\u09cd\u09b0\u09cd\u09af\u09be\u09a8\u09cd\u09a1\u09c7", "name_de": "Ribeira Grande", "name_en": "Ribeira Grande", "name_es": "Ribeira Grande", "name_fr": "Ribeira Grande", "name_el": "\u0394\u03ae\u03bc\u03bf\u03c2 \u03a1\u03b9\u03bc\u03c0\u03ad\u03b9\u03c1\u03b1 \u0393\u03ba\u03c1\u03ac\u03bd\u03c4\u03b5", "name_hi": "\u0930\u093f\u092c\u0947\u0930\u093e \u0917\u094d\u0930\u093e\u0902\u0921\u0947", "name_hu": "", "name_id": "Ribeira Grande", "name_it": "contea di Ribeira Grande", "name_ja": "\u30ea\u30d9\u30a4\u30e9\u30fb\u30b0\u30e9\u30f3\u30c7", "name_ko": "\ud788\ubca0\uc774\ub77c\uadf8\ub780\ub4dc \uc2dc", "name_nl": "Ribeira Grande", "name_pl": "Ribeira Grande", "name_pt": "Ribeira Grande", "name_ru": "\u0420\u0438\u0431\u0435\u0439\u0440\u0430-\u0413\u0440\u0430\u043d\u0434\u0435", "name_sv": "Ribeira Grande", "name_tr": "Riberie GRande", "name_vi": "Ribeira Grande", "name_zh": "\u5927\u91cc\u8c9d\u62c9\u7e23", "ne_id": 1159316347}}, {"type": "Feature", "geometry": {"type": "Polygon", "coordinates": [[[-24.98668247577032, 17.07886458989845], [-25.01512610599991, 17.04913971600007], [-25.019683397999927, 17.04901764500005], [-25.023915167999917, 17.045396226000037], [-25.042713995999918, 17.03847890800006], [-25.046986456999946, 17.03506094000005], [-25.055572068999936, 17.02480703300006], [-25.11587480399993, 16.99746328300006], [-25.143422003999945, 16.970038153000075], [-25.162953253999945, 16.94529857000009], [-25.187855597999942, 16.928168036000045], [-25.231312628999945, 16.923000393000052], [-25.269195115999935, 16.923000393000052], [-25.28083248599995, 16.920721747000073], [-25.289662238999938, 16.917181708000044], [-25.29869544199994, 16.91738515800006], [-25.31078040299991, 16.92609284100007], [-25.313384568999936, 16.93846263200004], [-25.31387285099993, 17.00495026200008], [-25.32754472599993, 17.028225002000056], [-25.33104407499991, 17.030951239000046], [-25.34829667899993, 17.034125067000048], [-25.354847785999937, 17.03847890800006], [-25.36042232999995, 17.055243231000077], [-25.355580206999946, 17.069566148000092], [-25.330922003999945, 17.096828518000052], [-25.316802537999934, 17.10610586100006], [-25.30215410099993, 17.10805898600006], [-25.289133266999954, 17.10700104400007], [-25.279774542999917, 17.10732656500005], [-25.269602016999954, 17.11432526200008], [-25.245350715263328, 17.136704820371165], [-25.191059344812913, 17.107606637736126], [-25.158313579408173, 17.085776128365637], [-25.11266796735282, 17.103637454704767], [-25.072976131643145, 17.113560413182483], [-25.028322815345632, 17.105622046220446], [-25.000538529629466, 17.087760719881317], [-24.98668247577032, 17.07886458989845]]]}, "properties": {"featurecla": "Admin-1 scale rank", "scalerank": 5, "adm1_code": "CPV-5060", "diss_me": 5060, "iso_3166_2": "CV-PN", "wikipedia": "http://en.wikipedia.org/wiki/Porto_Novo_(Cape_Verdean_municipality)", "iso_a2": "CV", "adm0_sr": 3, "name": "Porto Novo", "name_alt": "", "name_local": "", "type": "", "type_en": "", "code_local": "13", "code_hasc": "CV.PN", "note": "", "hasc_maybe": "", "region": "Ilhas de Barlavento", "region_cod": "CV-B", "provnum_ne": 0, "gadm_level": 0, "check_me": 0, "datarank": 10, "abbrev": "", "postal": "", "area_sqkm": 0, "sameascity": -99, "labelrank": 20, "name_len": 10, "mapcolor9": 4, "mapcolor13": 11, "fips": "CV21", "fips_alt": "", "woe_id": 56051556, "woe_label": "Porto Novo, CV, Cape Verde", "woe_name": "Porto Novo", "latitude": 17.0173, "longitude": -25.2258, "sov_a3": "CPV", "adm0_a3": "CPV", "adm0_label": 2, "admin": "Cape Verde", "geonunit": "Cape Verde", "gu_a3": "CPV", "gn_id": 7602868, "gn_name": "Concelho do Porto Novo", "gns_id": 10872166, "gns_name": "Porto Novo, Concelho do", "gn_level": 1, "gn_region": "", "gn_a1_code": "CV.21", "region_sub": "", "sub_code": "", "gns_level": 1, "gns_lang": "por", "gns_adm1": "CV21", "gns_region": "", "min_label": 11, "max_label": 11, "min_zoom": 11, "wikidataid": "Q1552897", "name_ar": "\u0628\u0648\u0631\u062a\u0648 \u0646\u0648\u0641\u0648", "name_bn": "\u09aa\u09cb\u09b0\u09cd\u099f\u09cb \u09a8\u09cb\u09ad\u09cb", "name_de": "Porto Novo", "name_en": "Porto Novo", "name_es": "Porto Novo", "name_fr": "Porto Novo", "name_el": "\u0394\u03ae\u03bc\u03bf\u03c2 \u03a0\u03cc\u03c1\u03c4\u03bf \u039d\u03cc\u03b2\u03bf", "name_hi": "\u092a\u094b\u0930\u094d\u091f\u094b \u0928\u094b\u0935\u094b", "name_hu": "", "name_id": "Porto Novo", "name_it": "contea di Porto Novo", "name_ja": "\u30dd\u30eb\u30c8\u30fb\u30ce\u30dc", "name_ko": "\ud3ec\ub974\ud22c\ub178\ubd80 \uc2dc", "name_nl": "Porto Novo", "name_pl": "Porto Novo", "name_pt": "Porto Novo", "name_ru": "\u041f\u043e\u0440\u0442\u043e-\u041d\u043e\u0432\u043e", "name_sv": "Porto Novo", "name_tr": "Porto Novo", "name_vi": "Porto Novo", "name_zh": "\u6ce2\u591a\u8afe\u4f0f\u7e23", "ne_id": 1159316345}}, {"type": "Feature", "geometry": {"type": "Polygon", "coordinates": [[[-25.025868292999917, 17.144924221000053], [-25.02057857999995, 17.140366929000038], [-24.99705969999991, 17.13418203300006], [-24.99176998599995, 17.130926825000074], [-24.988677537999934, 17.12571849200009], [-24.974964972999942, 17.114488023000092], [-24.971262173999946, 17.10732656500005], [-24.973011847999942, 17.096625067000048], [-24.978993292999917, 17.08690013200004], [-24.98668247577032, 17.07886458989845], [-25.000538529629466, 17.087760719881317], [-25.028322815345632, 17.105622046220446], [-25.072976131643145, 17.113560413182483], [-25.054122508646856, 17.127452556490255], [-25.038245774722725, 17.138367811625187], [-25.025868292999917, 17.144924221000053]]]}, "properties": {"featurecla": "Admin-1 scale rank", "scalerank": 5, "adm1_code": "CPV-5062", "diss_me": 5062, "iso_3166_2": "CV-PA", "wikipedia": "http://en.wikipedia.org/wiki/Paul_(Cape_Verde)", "iso_a2": "CV", "adm0_sr": 3, "name": "Paul", "name_alt": "", "name_local": "", "type": "", "type_en": "", "code_local": "12", "code_hasc": "CV.PA", "note": "", "hasc_maybe": "", "region": "Ilhas de Barlavento", "region_cod": "CV-B", "provnum_ne": 0, "gadm_level": 0, "check_me": 0, "datarank": 10, "abbrev": "", "postal": "", "area_sqkm": 0, "sameascity": -99, "labelrank": 20, "name_len": 4, "mapcolor9": 4, "mapcolor13": 11, "fips": "CV05", "fips_alt": "", "woe_id": 20069964, "woe_label": "Paul, CV, Cape Verde", "woe_name": "Paul", "latitude": 17.1179, "longitude": -25.0151, "sov_a3": "CPV", "adm0_a3": "CPV", "adm0_label": 2, "admin": "Cape Verde", "geonunit": "Cape Verde", "gu_a3": "CPV", "gn_id": 3374391, "gn_name": "Concelho do Paul", "gns_id": -1313410, "gns_name": "Paul", "gn_level": 1, "gn_region": "", "gn_a1_code": "CV.05", "region_sub": "", "sub_code": "", "gns_level": 1, "gns_lang": "por", "gns_adm1": "CV05", "gns_region": "", "min_label": 11, "max_label": 11, "min_zoom": 11, "wikidataid": "Q1475374", "name_ar": "\u0628\u0648\u0644", "name_bn": "\u09aa\u09b2", "name_de": "Paul", "name_en": "Paul", "name_es": "Paul", "name_fr": "Paul", "name_el": "\u0394\u03ae\u03bc\u03bf\u03c2 \u03a0\u03b1\u03bf\u03cd\u03bb", "name_hi": "\u092a\u0949\u0932", "name_hu": "", "name_id": "Paul", "name_it": "contea di Paul", "name_ja": "\u30d1\u30a6\u30eb", "name_ko": "\ud30c\uc6b8 \uc2dc", "name_nl": "Pa\u00fal", "name_pl": "Pa\u00fal", "name_pt": "Paul", "name_ru": "\u041f\u043e\u043b", "name_sv": "Concelho do Paul", "name_tr": "Paul", "name_vi": "Paul", "name_zh": "\u4fdd\u723e\u7e23", "ne_id": 1159316349}}, {"type": "Feature", "geometry": {"type": "Polygon", "coordinates": [[[-23.618337728203585, 15.105777836178163], [-23.607264802128896, 15.1035632511431], [-23.58068978080877, 15.098026788105756], [-23.57847519577365, 15.088061154998286], [-23.579976186751594, 15.08155686046075], [-23.58179707377593, 15.073666351820691], [-23.585118950878893, 15.055949670640757], [-23.605050217093833, 15.041554867463162], [-23.612038867599665, 15.040919536007777], [-23.629410653378955, 15.0393402824281], [-23.637028455199072, 15.049084947612243], [-23.64431555921567, 15.063051895628462], [-23.647959111223997, 15.081876912989117], [-23.64188652454345, 15.087342240551948], [-23.618337728203585, 15.105777836178163]]]}, "properties": {"featurecla": "Admin-1 scale rank", "scalerank": 5, "adm1_code": "CPV-5049", "diss_me": 5049, "iso_3166_2": "CV-SS", "wikipedia": "http://en.wikipedia.org/wiki/S%C3%A3o_Salvador_do_Mundo", "iso_a2": "CV", "adm0_sr": 3, "name": "S\u00e3o Salvador do Mundo", "name_alt": "", "name_local": "", "type": "", "type_en": "", "code_local": "72", "code_hasc": "CV.SS", "note": "", "hasc_maybe": "", "region": "Ilhas de Sotavento", "region_cod": "CV-S", "provnum_ne": 0, "gadm_level": 0, "check_me": 0, "datarank": 10, "abbrev": "", "postal": "SS", "area_sqkm": 0, "sameascity": -99, "labelrank": 20, "name_len": 21, "mapcolor9": 4, "mapcolor13": 11, "fips": "CV26", "fips_alt": "", "woe_id": 56051557, "woe_label": "", "woe_name": "S\u00e3o Salvador do Mundo", "latitude": 15.0678, "longitude": -23.6164, "sov_a3": "CPV", "adm0_a3": "CPV", "adm0_label": 2, "admin": "Cape Verde", "geonunit": "Cape Verde", "gu_a3": "CPV", "gn_id": 7602871, "gn_name": "Concelho de Sao Salvador do Mundo", "gns_id": 10874253, "gns_name": "Sao Salvador do Mundo, Concelho de", "gn_level": 1, "gn_region": "", "gn_a1_code": "CV.26", "region_sub": "", "sub_code": "", "gns_level": 1, "gns_lang": "por", "gns_adm1": "CV26", "gns_region": "", "min_label": 11, "max_label": 11, "min_zoom": 11, "wikidataid": "Q494877", "name_ar": "\u0633\u0627\u0648 \u0633\u0644\u0641\u0627\u062f\u0648\u0631 \u062f\u0648 \u0645\u0648\u0646\u062f\u0648", "name_bn": "\u09b8\u09be\u0993 \u09b8\u09be\u09b2\u09ad\u09be\u09a1\u09b0 \u09a1\u09c1 \u09ae\u09c1\u09a8\u09cd\u09a1\u09cb", "name_de": "S\u00e3o Salvador do Mundo", "name_en": "S\u00e3o Salvador do Mundo", "name_es": "S\u00e3o Salvador do Mundo", "name_fr": "S\u00e3o Salvador do Mundo", "name_el": "\u0394\u03ae\u03bc\u03bf\u03c2 \u03a3\u03ac\u03bf \u03a3\u03b1\u03bb\u03b2\u03b1\u03b4\u03cc\u03c1 \u03bd\u03c4\u03bf \u039c\u03bf\u03cd\u03bd\u03c4\u03bf", "name_hi": "\u0938\u093e\u0913 \u0938\u093e\u0932\u094d\u0935\u093e\u0921\u094b\u0930 \u0921\u094b \u092e\u0941\u0902\u0921\u094b", "name_hu": "", "name_id": "S\u00e3o Salvador do Mundo", "name_it": "contea di S\u00e3o Salvador do Mundo", "name_ja": "\u30b5\u30f3\u30fb\u30b5\u30eb\u30d0\u30c9\u30eb\u30fb\u30c9\u30fb\u30e0\u30f3\u30c9", "name_ko": "\uc0c1\uc0b4\ubc14\ub3c4\ub974\ub450\ubb38\ub450 \uc2dc", "name_nl": "S\u00e3o Salvador do Mundo", "name_pl": "S\u00e3o Salvador do Mundo", "name_pt": "S\u00e3o Salvador do Mundo", "name_ru": "\u0421\u0430\u043d-\u0421\u0430\u043b\u044c\u0432\u0430\u0434\u043e\u0440-\u0434\u043e-\u041c\u0443\u043d\u0434\u043e", "name_sv": "Concelho de S\u00e3o Salvador do Mundo", "name_tr": "Sao Salvador do Mundo", "name_vi": "S\u00e3o Salvador do Mundo", "name_zh": "\u8056\u85a9\u723e\u74e6\u591a\u8499\u591a\u7e23", "ne_id": 1159316319}}, {"type": "Feature", "geometry": {"type": "Polygon", "coordinates": [[[-23.612038867599665, 15.040919536007777], [-23.605050217093833, 15.041554867463162], [-23.585118950878893, 15.055949670640757], [-23.58179707377593, 15.073666351820691], [-23.579976186751594, 15.08155686046075], [-23.564157420428614, 15.074589809871838], [-23.54958321329468, 15.078840620098504], [-23.52643244520118, 15.05927154864304], [-23.543041833413895, 15.053735085605695], [-23.56186580756099, 15.03823298946088], [-23.576260610738586, 15.022730894215385], [-23.596191876953583, 15.011657968140696], [-23.611693973098397, 15.024945479250448], [-23.612038867599665, 15.040919536007777]]]}, "properties": {"featurecla": "Admin-1 scale rank", "scalerank": 5, "adm1_code": "CPV-5050", "diss_me": 5050, "iso_3166_2": "CV-SO", "wikipedia": "http://en.wikipedia.org/wiki/S%C3%A3o_Louren%C3%A7o_dos_%C3%93rg%C3%A3os", "iso_a2": "CV", "adm0_sr": 3, "name": "S\u00e3o Louren\u00e7o dos \u00d3rg\u00e3os", "name_alt": "", "name_local": "", "type": "", "type_en": "", "code_local": "73", "code_hasc": "CV.LO", "note": "", "hasc_maybe": "", "region": "Ilhas de Sotavento", "region_cod": "CV-S", "provnum_ne": 0, "gadm_level": 0, "check_me": 0, "datarank": 10, "abbrev": "", "postal": "SO", "area_sqkm": 0, "sameascity": -99, "labelrank": 20, "name_len": 23, "mapcolor9": 4, "mapcolor13": 11, "fips": "CV25", "fips_alt": "", "woe_id": 56051560, "woe_label": "", "woe_name": "S\u00e3o Louren\u00e7o dos \u00d3rg\u00e3os", "latitude": 15.0439, "longitude": -23.5781, "sov_a3": "CPV", "adm0_a3": "CPV", "adm0_label": 2, "admin": "Cape Verde", "geonunit": "Cape Verde", "gu_a3": "CPV", "gn_id": 7602873, "gn_name": "Concelho de Sao Lourenco dos Orgaos", "gns_id": 10874276, "gns_name": "Sao Lourenco dos Orgaos, Concelho de", "gn_level": 1, "gn_region": "", "gn_a1_code": "CV.25", "region_sub": "", "sub_code": "", "gns_level": 1, "gns_lang": "por", "gns_adm1": "CV25", "gns_region": "", "min_label": 11, "max_label": 11, "min_zoom": 11, "wikidataid": "Q494726", "name_ar": "\u0633\u0627\u0648 \u0644\u0648\u0631\u064a\u0646\u0633\u0648 \u062f\u0648\u0633 \u0623\u0648\u0631\u063a\u0627\u0648\u0633", "name_bn": "\u09b8\u09c7\u09a8\u09cd\u099f \u09b2\u09b0\u09c7\u09a8\u09cd\u09b8 \u09a6\u09cb\u09b8 \u0985\u09b0\u0997\u09cd\u09af\u09be\u09b8", "name_de": "S\u00e3o Louren\u00e7o dos \u00d3rg\u00e3os", "name_en": "S\u00e3o Louren\u00e7o dos \u00d3rg\u00e3os", "name_es": "S\u00e3o Louren\u00e7o dos \u00d3rg\u00e3os", "name_fr": "S\u00e3o Louren\u00e7o dos \u00d3rg\u00e3os", "name_el": "\u0394\u03ae\u03bc\u03bf\u03c2 \u03a3\u03ac\u03bf \u039b\u03bf\u03c5\u03c1\u03ad\u03bd\u03c3\u03bf \u03bd\u03c4\u03bf\u03c2 \u039f\u03c1\u03b3\u03ba\u03ac\u03bf\u03c2", "name_hi": "\u0938\u093e\u0913 \u0932\u094b\u0930\u0947\u0902\u0915\u094b \u0921\u0949\u0938 \u0911\u0930\u0947\u0917\u094b\u0938", "name_hu": "", "name_id": "S\u00e3o Louren\u00e7o dos \u00d3rg\u00e3os", "name_it": "contea di S\u00e3o Louren\u00e7o dos \u00d3rg\u00e3os", "name_ja": "\u30b5\u30f3\u30fb\u30ed\u30fc\u30ec\u30f3\u30bd\u30fb\u30c9\u30b9\u30fb\u30aa\u30eb\u30ac\u30f3\u30b9", "name_ko": "\uc0c1\ub85c\ub80c\uc218\ub450\uc2a4\uc624\ub974\uac15\uc2a4 \uc2dc", "name_nl": "S\u00e3o Louren\u00e7o dos \u00d3rg\u00e3os", "name_pl": "S\u00e3o Louren\u00e7o dos \u00d3rg\u00e3os", "name_pt": "S\u00e3o Louren\u00e7o dos \u00d3rg\u00e3os", "name_ru": "\u0421\u0430\u043d-\u041b\u043e\u0440\u0435\u043d\u0441\u0443-\u0434\u0443\u0448-\u041e\u0440\u0433\u0430\u0443\u0448", "name_sv": "S\u00e3o Louren\u00e7o dos \u00d3rg\u00e3os", "name_tr": "Sao Lourenco dos Orgaos", "name_vi": "Sao Lourenco dos Orgaos", "name_zh": "\u8056\u6d1b\u502b\u7d22\u7e23", "ne_id": 1159316321}}]}